Workbook
Name Complexity: #REF!
Name DocumentTypes: [1]Lookups!$A$24:$A$28
Name Open: #REF!
Name Requirementstatus: #REF!
Name Status: #REF!
Name YesNo: [2]Lookups!$A$1:$A$2

Sheet Table of Contents
A1: TABLE OF CONTENTS
A2: Client: | B2: SECURA Insurance Companies
A3: Phase: | B3: Product Simplification
A4: # | B4: TAB NAME | C4: DESCRIPTION
A5: 2 | B5: Version History | C5: Anytime you make a change or update to the document
A6: 3 | B6: Definitions | C6: These should remain unchanged, use this as a reference/glossary to understand terms
A7: 4 | B7: Product Contacts | C7: Who are the client Product SME's that helped define the Product Strategy
A8: 5 | B8: Product Inventory | C8: A single source view of ALL Products/Processes during the Product Strategy & Rationalization phases
A9: 6 | B9: Product Component Model | C9: The focal point of this document, where you document the Product Architecture. This is the foundation that comes out of your Product Definition & Development phase
A10: 7 | B10: PCM Dropdowns | C10: This should stay unchanged, and should remain as a hidden tab
A13: TABS LEGEND | D13: MAIN COLUMNS LEGEND | G13: Start here
B14: Administrative | E14: Product Hierarchy
B15: Supplemental/Supporting | E15: Product Details
B16: Primary/Main Focal Point | E16: Product Applicability
B17: Hidden/Unchanged

Sheet Version History
A1: VERSION HISTORY
A2: Client: | B2: ='Table of Contents'!B2 -> SECURA Insurance Companies
A3: Phase: | B3: ='Table of Contents'!B3 -> Product Simplification
A4: DATE | B4: VERSION | C4: SUMMARY OF UPDATE | D4: NAME
A5: 44854 | B5: 1 | C5: Created this example for you | D5: Tulio

Sheet Definitions
A1: DEFINITIONS - PRODUCT COMPONENT MODEL
A2: Client: | B2: ='Table of Contents'!B2 -> SECURA Insurance Companies
A3: Phase: | B3: ='Table of Contents'!B3 -> Product Simplification
A4: COLUMN NAME | B4: DEFINITION | C4: EXAMPLE
A5: Product | B5: A Product is a Line of Business or multiple Lines of Business presented for sale and distribution in the market by an insurer
A6: LOB | B6: A Line of Business (LOB) is a specific Product, which contains a group of related Coverages
A7: Coverage | B7: Coverage is the scope of protection against a specific loss or liability within a Line of Business
A8: Sub-Coverage | B8: Sub-Coverage is the scope of proection against a specific loss or liability, and has a parent-child relationship with a Coverage. Often times offered as supplementary or optional for additional premium
A9: Claims Basis | B9: Occurrence: An occurrence policy protects a business from any covered incident that happens during the policy period—regardless of when a claim is reported. Claims-made: A claims-made policy provides coverage for claims that occur—and are reported—within the specific time period set forth by the policy. | C9: Occurrence: Bob the business owner purchased an occurrence policy in 2015 but switched to a new form of coverage in 2020. Bob got sued in 2022 for an incident that occurred in 2017. In this instance, Bob is still covered by his original occurrence policy, because it was active at the time of the incident. Claims-made: Bob the businessman purchased a claims-made policy in 2015 and continued coverage through 2017, then cancels. He does not purchase any extension (tail coverage) on the policy’s original limits. In 2018, Bob is sued for an incident that occurred in 2016. Since the claims-made policy is no longer in effect and he did not purchase tail coverage, Bob is the liable party—meaning he is obligated to pay for damages, as his former insurance carrier does not cover it.
A10: Coverage Requirement | B10: Determines whether the Coverage is Mandatory or Optional Mandatory: Mandatory insurance is any type of insurance that an individual or business is legally required to buy. Optional: Any type of insurance that is not required, and may be added for additional premium. | C10: Mandatory: Insurance is mandatory for individuals and businesses that want to engage in certain financially risky activities, such as operating an automobile, owning a home or operating a business with employees. Optional: Any type of insurance that is not required, and may be added for additional premium.
A11: Coverage Scope | B11: First Party: First-party insurance is obtained for the policyholder (otherwise known as the named insured) to cover losses or damages to the policyholder’s property or themselves. Third Party: Third-party insurance is purchased to protect the insured against liability for losses or damages that the insured causes to another individual or to their property. | C11: First Party: Common types of first-party insurance claims -- Health Insurance, Medical payments under an Auto or Homeowner policy, PIP under Auto, Underinsured or Uninsured motorist. Third Party: Common types of third-party insurance claims -- CGL coverage, Liability under Auto, Commercial Auto, Umbrella policies, Professional Liability, Product Liability, Animal Liability insurance.
A12: Coverage Effect | B12: What effect does this coverage have? (Rebecca/Robert could you please help us define these?) Grants Coverage Restricts Broadens Amends Administrative
A13: Premium Generating? | B13: Whether there is any impact to Premium (i.e. Additional premium, etc…) Yes: Yes this impacts/generates Premium No: This does not impact/generate any Premium
A14: Rating Bureau? | B14: Determines whether this carrier participates in any organization that standardizes insurance underwriting. | C14: Examples include: ISO, ACORD, AAIS, NCCI. Any organization that provides standardized Forms, Insurance Raters, and aids with filings and regulations.
A15: Proprietary | B15: Determines if they handle all of their underwriting in-house. | C15: In this case: The carrier has their own Raters, Forms, carries out their own filings, and has a dedicated team that deals with regulators.
A16: No. of Forms | B16: Total count of all coverage forms per Product Hierarchy
A17: State Applicability | B17: The State(s) to which the Product applies
A18: W.R.A.P | B18: SECURA's proprietary endorsement, which adds coverages/limits/etc... With Reliable Added Protection
A20: Insurance Guiding Principles | B20: If there is no Limit, Premium, Deductible, then not included in this document (i.e. Exclusions)

Sheet Product Contacts
A1: PRODUCT CONTACTS
A2: Client: | B2: ='Table of Contents'!B2 -> SECURA Insurance Companies
A3: Phase: | B3: ='Table of Contents'!B3 -> Product Simplification
A4: PRODUCT | B4: PRODUCT OWNER | C4: EMAIL ADDRESS | D4: PHONE NUMBER | E4: DATE OF FIRST MEET
A5: Commercial Property | B5: Jeri Eveland | C5: Jeri_Eveland@SECURA.net | D5: (123)456-7890

Sheet Product Inventory
A1: PRODUCT INVENTORY
B2: Client: | C2: ='Table of Contents'!B2 -> SECURA Insurance Companies
B3: Phase: | C3: ='Table of Contents'!B3 -> Product Simplification
B4: OWNERSHIP | D4: POLICY | H4: PRICING/ACTUARIAL | L4: UNDERWRITING | P4: DOCUMENTS | T4: CLAIMS | X4: BILLING
F5: CURRENT | G5: TARGET | H5: CURRENT | I5: TARGET | J5: CURRENT | K5: TARGET | L5: CURRENT | M5: TARGET | N5: CURRENT | O5: TARGET | P5: CURRENT | Q5: TARGET | R5: CURRENT | S5: TARGET | V5: CURRENT | W5: TARGET | X5: CURRENT | Y5: TARGET
A6: # | B6: PRODUCT OWNER | C6: PRODUCT | D6: POLICY PREMIUM | E6: POLICY COUNT (Approximate) | F6: POLICY PROCESSING SYSTEM | H6: NUMBER OF RATING ALGORITHMS - STEPS | J6: NUMBER OF COVERAGES | L6: NUMBER OF WRITING COMPANIES | N6: NUMBER OF UNDERWRITING RULES | P6: NUMBER OF FORMS | R6: DOCUMENT STORAGE SYSTEM | T6: CLAIMS COUNTS (2021 Annual) | U6: CLAIMS COUNTS (Open as of June 2022) | V6: CLAIMS SYSTEM SUPPORTED | X6: BILLING SYSTEM SUPPORTED
A7: 1 | C7: Commercial Property Product | D7: 500K | E7: 0 | F7: PowerWriter
A8: 2
A9: 3
A10: 4 | C10: Product #2 | D10: 2M
A11: 5
A12: 6
A13: 7
A14: 8
A15: 9
A16: 10
A17: 11
A18: 12
A19: 13
A20: 14 | C20: Product #3
A21: 15
A22: 16
A23: 17 | C23: Product #4
A24: 18
A25: 19
A26: 20 | C26: Product #5
A27: 21
A28: 22
A29: 23 | C29: Product #6
A30: 24
A31: 25

Sheet Product Component Model
A2: Client Name:
A3: Phase:
B4: PRODUCT HEIRARCHY | F4: COVERAGE DETAILS | Q4: STATE APPLICABILITY
A5: ID | B5: PRODUCT | C5: LOB | D5: COVERAGE | E5: SUB COVERAGE | F5: COVERAGE FORM(S) | G5: FORM NUMBER | H5: EDITION DATE | I5: CLAIMS BASIS | J5: COVERAGE REQUIREMENT | K5: COVERAGE SCOPE | L5: COVERAGE EFFECT | M5: PREMIUM GENERATING? | N5: RATING BUREAU | O5: PROPRIETARY? | P5: CLAIMS EXPENSE W/I LIMIT? | Q5: ALL 14 | R5: AZ | S5: CO | T5: IL | U5: IN | V5: IA | W5: KS | X5: KY | Y5: MI | Z5: MN | AA5: MO | AB5: ND | AC5: PA | AD5: UT | AE5: WI | AF5: QUESTIONS / COMMENTS
A6: PRCOV001.0 | B6: Monoline Building and Personal Property | C6: Commercial Property | D6: Building | F6: Building and Personal Property | G6: CP 00 10 | H6: 06/07
A7: PR.COV001.0 | B7: Monoline Building and Personal Property | C7: Commercial Property | D7: Building | F7: Building and Personal Property | G7: CP 00 10 | H7: 06/07
A8: PR.COV001.0 | B8: Monoline Building and Personal Property | C8: Commercial Property | D8: Building | F8: Building and Personal Property | G8: CP 00 10 | H8: 06/07 | I8: Occurrence | J8: Mandatory | K8: First Party | L8: Grants Coverage | M8: Yes | N8: ISO | O8: No
A9: PR.COV001.1 | B9: Monoline Building and Personal Property | C9: Commercial Property | D9: Building | E9: Preservation Of Property | F9: Building and Personal Property | G9: CP 00 10 | H9: 06/07 | I9: Occurrence | J9: Optional | K9: First Party | L9: Broadens | N9: ISO | O9: No
A10: PR.COV001.2 | B10: Monoline Building and Personal Property | C10: Commercial Property | D10: Building | E10: Outdoor Signs | F10: Building and Personal Property | G10: CP 00 10 | H10: 06/07 | I10: Occurrence | J10: Optional | K10: First Party | L10: Broadens | N10: ISO | O10: No | AF10: Additional Coverage Forms: Outdoor Signs Endorsement, Universal Wrap, Human Services Wrap
A11: PR.COV001.3 | B11: Monoline Building and Personal Property | C11: Commercial Property | D11: Building | E11: Newly Acquired Or Constructed Property | F11: Building and Personal Property | G11: CP 00 10 | H11: 06/07 | I11: Occurrence | J11: Optional | K11: First Party | L11: Broadens | N11: ISO | O11: No | AF11: Additional Coverage Forms: Universal Wrap Elite Universal Wrap
A12: PR.COV001.4 | B12: Monoline Building and Personal Property | C12: Commercial Property | D12: Building | E12: Increased Cost Of Construction | F12: Building and Personal Property | G12: CP 00 10 | H12: 06/07 | I12: Occurrence | J12: Optional | K12: First Party | L12: Broadens | N12: ISO | O12: No | AF12: Additional Coverage Forms: Ordinance or Law Coverage Endorsement, Universal WRAP, Human Services WRAP, Golf Course Wrap
A13: PR.COV001.5 | B13: Monoline Building and Personal Property | C13: Commercial Property | D13: Building | E13: Debris Removal | F13: Building and Personal Property | G13: CP 00 10 | H13: 06/07 | I13: Occurrence | J13: Optional | K13: First Party | L13: Broadens | N13: ISO | O13: No
A14: PR.COV001.6 | B14: Monoline Building and Personal Property | C14: Commercial Property | D14: Building | E14: Fire Department Service Charge | F14: Building and Personal Property | G14: CP 00 10 | H14: 06/07 | I14: Occurrence | J14: Optional | K14: First Party | L14: Broadens | N14: ISO | O14: No
A15: PR.COV001.7 | B15: Monoline Building and Personal Property | C15: Commercial Property | D15: Building | E15: Volcanic Eruption | F15: Earthquake and Volcanic Eruption Endorsement | G15: CP 10 40 | H15: 08/99 | I15: Occurrence | J15: Optional | K15: First Party | L15: Grants Coverage | M15: Yes | N15: ISO | O15: No
A16: PR.COV001.8 | B16: Monoline Building and Personal Property | C16: Commercial Property | D16: Building | E16: Sprinkler Leakage | F16: Earthquake and Volcanic Eruption Endorsement | G16: CP 10 40 | H16: 02/19 | I16: Occurrence | J16: Optional | K16: First Party | L16: Grants Coverage | M16: Yes | N16: ISO | O16: No | AF16: Additional Coverage Forms: Human Services WRAP
A17: PR.COV001.9 | B17: Monoline Building and Personal Property | C17: Commercial Property | D17: Building | E17: Utility Services | F17: Utility Services - Direct Damage Endorsement | G17: CP 04 17 | H17: 10/12 | I17: Occurrence | J17: Optional | K17: First Party | L17: Grants Coverage | M17: Yes | N17: ISO | O17: No | AF17: Additional Coverage Forms: Human Services WRAP
A18: PR.COV001.10 | B18: Monoline Building and Personal Property | C18: Commercial Property | D18: Building | E18: Flood | F18: Flood Coverage Endorsement | G18: CP 10 65 | H18: 10/12 | I18: Occurrence | J18: Optional | K18: First Party | L18: Grants Coverage | N18: ISO | O18: No
A19: PR.COV001.11 | B19: Monoline Building and Personal Property | C19: Commercial Property | D19: Building | E19: Outdoor Trees, Shrubs & Plants | F19: Outdoor Trees, Shrubs & Plants Endorsement | G19: CP 14 30 | H19: 10/12 | I19: Occurrence | J19: Optional | K19: First Party | L19: Grants Coverage | M19: Yes | N19: ISO | O19: No | AF19: Additional Coverage Forms: Universal Wrap Coverage Form, Elite Wrap Coverage Form, Human Services Wrap, Inn Wrap, Golf Course Wrap
A20: PR.COV001.12 | B20: Monoline Building and Personal Property | C20: Commercial Property | D20: Building | E20: Fences And Antennas | F20: Outdoor Trees, Shrubs & Plants Endorsement | G20: CPT 90 99 | H20: 01/13 | I20: Occurrence | J20: Optional | K20: First Party | L20: Grants Coverage | M20: Yes | N20: ISO | O20: Yes | AF20: Additional Coverage Forms: Universal Wrap Coverage Form Elite Wrap Coverage Form Human Services Wrap Fences and Antennas
A21: PR.COV001.13 | B21: Monoline Building and Personal Property | C21: Commercial Property | D21: Building | E21: Green Upgrades | F21: Increased Cost of Loss and Related Expenses for Green Upgrades Endorsement | G21: CP 04 02 | H21: 10/12 | I21: Occurrence | J21: Optional | K21: First Party | L21: Grants Coverage | M21: Yes | N21: ISO | O21: No
A22: PR.COV001.14 | B22: Monoline Building and Personal Property | C22: Commercial Property | D22: Building | E22: Related Expenses | F22: Increased Cost of Loss and Related Expenses for Green Upgrades Endorsement | G22: CP 04 02 | H22: 10/12 | I22: Occurrence | J22: Optional | K22: First Party | L22: Grants Coverage | M22: Yes | N22: ISO | O22: No
A23: PR.COV001.15 | B23: Monoline Building and Personal Property | C23: Commercial Property | D23: Building | E23: Property Damage - Water Back-Up And Sump Overflow (Not Flood-Related) | F23: Water Back-up And Sump Overflow (Not Flood-Related) Endorsement | G23: CPE 06 96 | H23: 01/13 | I23: Occurrence | J23: Optional | K23: First Party | L23: Broadens | M23: Yes | N23: N/A
A24: PR.COV001.16 | B24: Monoline Building and Personal Property | C24: Commercial Property | D24: Building | E24: Public Safety Service Charges | F24: Universal Wrap | G24: CPT 90 99 | H24: 01/13 | I24: Occurrence | J24: Optional | K24: First Party | L24: Amends | N24: N/A | O24: Yes | AF24: This coverage replaces Fire Department Service Charge with ALL Public Service Charges. Additional Coverage Forms: Elite Universal WRAP, Human Services Wrap
A25: PR.COV001.17 | B25: Monoline Building and Personal Property | C25: Commercial Property | D25: Building | E25: Lock Replacement Due To Theft Of Keys Or Transmitters | F25: Universal Wrap | G25: CPT 90 99 | H25: 01/13 | I25: Occurrence | J25: Optional | K25: First Party | L25: Amends | N25: N/A | O25: Yes | AF25: Additional Coverage Forms: Elite Universal Wrap Coverage Form Human Services Wrap
A26: PR.COV001.18 | B26: Monoline Building and Personal Property | C26: Commercial Property | D26: Building | E26: Tenant Glass Breakage | F26: Universal Wrap | G26: CPT 90 99 | H26: 01/13 | I26: Occurrence | J26: Optional | K26: First Party | L26: Grants Coverage | M26: Yes | N26: N/A | O26: Yes | AF26: Additional Coverage Forms: Elite Wrap Coverage Form
A27: PR.COV001.19 | B27: Monoline Building and Personal Property | C27: Commercial Property | D27: Building | E27: Unscheduled Structures (Garages, Storage Buildings And Other Structures) | F27: Universal Wrap | G27: CPT 90 99 | H27: 01/13 | I27: Occurrence | J27: Optional | K27: First Party | L27: Grants Coverage | M27: Yes | N27: N/A | O27: Yes | AF27: Additional Coverage Forms: Elite Wrap Coverage Form
A28: PR.COV001.20 | B28: Monoline Building and Personal Property | C28: Commercial Property | D28: Building | E28: Tenant Building | F28: Universal Wrap | G28: CPT 90 99 | H28: 01/13 | I28: Occurrence | J28: Optional | K28: First Party | L28: Grants Coverage | N28: N/A | O28: Yes
A29: PR.COV001.21 | B29: Monoline Building and Personal Property | C29: Commercial Property | D29: Building | E29: Contract Penalty Costs | F29: Elite Universal Wrap | G29: CPT 79 99 | H29: 01/13 | I29: Occurrence | J29: Optional | K29: First Party | L29: Grants Coverage | N29: N/A | O29: Yes
A30: PR.COV001.22 | B30: Monoline Building and Personal Property | C30: Commercial Property | D30: Building | E30: Realty Tax-Increased Assessment | F30: Elite Universal Wrap | G30: CPT 79 99 | H30: 01/13 | I30: Occurrence | J30: Optional | K30: First Party | L30: Grants Coverage | N30: N/A | O30: Yes
A31: PR.COV001.23 | B31: Monoline Building and Personal Property | C31: Commercial Property | D31: Building | E31: Security After Loss | F31: Elite Universal Wrap | G31: CPT 79 99 | H31: 01/13 | I31: Occurrence | J31: Optional | K31: First Party | L31: Grants Coverage | N31: N/A | O31: Yes
A32: PR.COV001.24 | B32: Monoline Building and Personal Property | C32: Commercial Property | D32: Building | E32: Vacancy Permit | F32: Vacancy Permit | G32: CP 04 50 | H32: 07/88 | I32: Occurrence | J32: Optional | K32: First Party
A33: PR.COV001.25 | B33: Monoline Building and Personal Property | C33: Commercial Property | D33: Building | E33: Claim Data Or Inventory Expense | F33: Human Services Wrap | G33: CPT 35 00 | H33: 11/20 | I33: Occurrence | J33: Optional | K33: First Party | L33: Grants Coverage | N33: N/A | O33: Yes | AF33: Additional Coverage Forms: Golf Course Wrap
A34: PR.COV001.26 | B34: Monoline Building and Personal Property | C34: Commercial Property | D34: Building | E34: Swimming Pools And Inground Sprinkler Systems | F34: Golf Course Property Wrap | G34: CPT 48 00 | H34: 04/21
A35: PR.COV001.27 | B35: Monoline Building and Personal Property | C35: Commercial Property | D35: Building | E35: Theft Of Telephone Or Dataline Services | F35: Golf Course Property Wrap | G35: CPT 48 00 | H35: 04/21 | I35: Occurrence | J35: Optional | K35: First Party | L35: Grants Coverage | M35: Yes | N35: N/A | O35: Yes
A36: PR.COV002.0 | B36: Monoline Building and Personal Property | C36: Commercial Property | D36: Ordinance or Law | E36: Ordinance Or Law | F36: Ordinance or Law Coverage Endorsement | G36: CP 04 05 | H36: 04/02 | I36: Occurrence | J36: Optional | K36: First Party | L36: Grants Coverage | M36: Yes | N36: N/A | O36: Yes | AF36: Move down
A37: PR.COV002.1 | B37: Monoline Building and Personal Property | C37: Commercial Property | D37: Ordinance or Law | E37: Coverage For Loss To The Undamaged Portion Of The Building | F37: Ordinance or Law Coverage Endorsement | G37: CP 04 05 | H37: 09/17 | I37: Occurrence | J37: Optional | K37: First Party | L37: Grants Coverage | M37: Yes | N37: ISO | O37: No | AF37: Additional Coverage Forms: Functional Building Valuation Endorsement, Universal Wrap, Elite Wrap
A38: PR.COV002.2 | B38: Monoline Building and Personal Property | C38: Commercial Property | D38: Ordinance or Law | E38: Demolition Cost | F38: Ordinance or Law Coverage Endorsement | G38: CP 04 05 | H38: 09/17 | I38: Occurrence | J38: Optional | K38: First Party | L38: Grants Coverage | M38: Yes | N38: ISO | O38: No | AF38: Additional Coverage Forms: Universal WRAP, Elite Universal WRAP, Human Services WRAP, Golf Course Wrap
A39: PR.COV002.3 | B39: Monoline Building and Personal Property | C39: Commercial Property | D39: Ordinance or Law | E39: Increased Cost Of Construction | F39: Ordinance or Law Coverage Endorsement | G39: CP 04 05 | H39: 09/17 | I39: Occurrence | J39: Optional | K39: First Party | L39: Grants Coverage | M39: Yes | N39: ISO | O39: No | AF39: Additional Coverage Forms: Universal WRAP, Elite Universal WRAP, Human Services WRAP, Golf Course Wrap
A40: PR.COV003.0 | B40: Monoline Building and Personal Property | C40: Commercial Property | D40: Business Personal Property | F40: Building and Personal Property | G40: CP 00 10 | H40: 06/07 | I40: Occurrence | J40: Mandatory | K40: First Party | L40: Grants Coverage | M40: Yes | N40: ISO | O40: No
A41: PR.COV003.1 | B41: Monoline Building and Personal Property | C41: Commercial Property | D41: Business Personal Property | E41: Preservation Of Property | F41: Building and Personal Property | G41: CP 00 10 | H41: 06/07 | I41: Occurrence | J41: Optional | K41: First Party | L41: Broadens | N41: ISO | O41: No
A42: PR.COV003.2 | B42: Monoline Building and Personal Property | C42: Commercial Property | D42: Business Personal Property | E42: Outdoor Signs | F42: Building and Personal Property | G42: CP 00 10 | H42: 06/07 | I42: Occurrence | J42: Optional | K42: First Party | L42: Broadens | N42: ISO | O42: No | AF42: Additional Coverage Forms: Outdoor Signs Endorsement, Universal Wrap, Human Services Wrap
A43: PR.COV003.3 | B43: Monoline Building and Personal Property | C43: Commercial Property | D43: Business Personal Property | E43: Newly Acquired Or Constructed Property | F43: Building and Personal Property | G43: CP 00 10 | H43: 06/07 | I43: Occurrence | J43: Optional | K43: First Party | L43: Broadens | N43: ISO | O43: No | AF43: Additional Coverage Forms: Universal Wrap, Elite Universal Wrap
A44: PR.COV003.4 | B44: Monoline Building and Personal Property | C44: Commercial Property | D44: Business Personal Property | E44: Electronic Data | F44: Building and Personal Property | G44: CP 00 10 | H44: 06/07 | I44: Occurrence | J44: Optional | K44: First Party | L44: Broadens | N44: ISO | O44: No
A45: PR.COV003.5 | B45: Monoline Building and Personal Property | C45: Commercial Property | D45: Business Personal Property | E45: Personal Effects And Property Of Others | F45: Building and Personal Property | G45: CP 00 10 | H45: 06/07 | I45: Occurrence | J45: Optional | K45: First Party | L45: Broadens | N45: ISO | O45: No | AF45: Additional Coverage Forms: Universal Wrap, Elite Universal Wrap, Human Services Wrap, Golf Course Wrap
A46: PR.COV003.6 | B46: Monoline Building and Personal Property | C46: Commercial Property | D46: Business Personal Property | E46: Valuable Papers & Records (Other Than Electronic Data) | F46: Building and Personal Property | G46: CP 00 10 | H46: 06/07 | I46: Occurrence | J46: Optional | K46: First Party | L46: Broadens | N46: ISO | O46: No | AF46: Additional Coverage Forms: Universal Wrap, Elite Universal Wrap, Human Services Wrap, Golf Course Wrap
A47: PR.COV003.7 | B47: Monoline Building and Personal Property | C47: Commercial Property | D47: Business Personal Property | E47: Property Off-Premises | F47: Building and Personal Property | G47: CP 00 10 | H47: 06/07 | I47: Occurrence | J47: Optional | K47: First Party | L47: Broadens | N47: ISO | O47: No | AF47: Additional Coverage Forms: Universal Wrap Human Services Wrap
A48: PR.COV003.8 | B48: Monoline Building and Personal Property | C48: Commercial Property | D48: Business Personal Property | E48: Non-Owned Detached Trailers | F48: Building and Personal Property | G48: CP 00 10 | H48: 06/07 | I48: Occurrence | J48: Optional | K48: First Party | L48: Broadens | N48: ISO | O48: No
A49: PR.COV003.9 | B49: Monoline Building and Personal Property | C49: Commercial Property | D49: Business Personal Property | E49: Debris Removal | F49: Building and Personal Property | G49: CP 00 10 | H49: 06/07 | I49: Occurrence | J49: Optional | K49: First Party | L49: Broadens | N49: ISO | O49: No
A50: PR.COV003.10 | B50: Monoline Building and Personal Property | C50: Commercial Property | D50: Business Personal Property | E50: Fire Department Service Charge | F50: Building and Personal Property | G50: CP 00 10 | H50: 06/07 | I50: Occurrence | J50: Optional | K50: First Party | L50: Broadens | N50: ISO | O50: No
A51: PR.COV003.11 | B51: Monoline Building and Personal Property | C51: Commercial Property | D51: Business Personal Property | E51: Computer | F51: Computer Amendatory Endorsement | G51: CPE 01 00 | H51: 01/13 | I51: Occurrence | J51: Optional | K51: First Party | L51: Amends | N51: N/A | O51: Yes
A52: PR.COV003.12 | B52: Monoline Building and Personal Property | C52: Commercial Property | D52: Business Personal Property | E52: Electronic Data | F52: Computer Amendatory Endorsement | G52: CPE 01 00 | H52: 01/13 | I52: Occurrence | J52: Optional | K52: First Party | L52: Amends | N52: N/A | O52: Yes
A53: PR.COV003.13 | B53: Monoline Building and Personal Property | C53: Commercial Property | D53: Business Personal Property | E53: Interruption Of Computer Operations | F53: Computer Amendatory Endorsement | G53: CPE 01 00 | H53: 01/13 | I53: Occurrence | J53: Optional | K53: First Party | L53: Amends | N53: N/A | O53: Yes
A54: PR.COV003.14 | B54: Monoline Building and Personal Property | C54: Commercial Property | D54: Business Personal Property | E54: False Pretense Computer | F54: Computer Amendatory Endorsement | G54: CPE 01 00 | H54: 01/13 | I54: Occurrence | J54: Optional | K54: First Party | L54: Amends | N54: N/A | O54: Yes
A55: PR.COV003.15 | B55: Monoline Building and Personal Property | C55: Commercial Property | D55: Business Personal Property | E55: Earthquake | F55: Earthquake and Volcanic Eruption Endorsement | G55: CP 10 40 | H55: 02/19 | I55: Occurrence | J55: Optional | K55: First Party | L55: Grants Coverage | M55: Yes | N55: ISO | O55: No
A56: PR.COV003.16 | B56: Monoline Building and Personal Property | C56: Commercial Property | D56: Business Personal Property | E56: Volcanic Eruption | F56: Earthquake and Volcanic Eruption Endorsement | G56: CP 10 40 | H56: 02/19 | I56: Occurrence | J56: Optional | K56: First Party | L56: Grants Coverage | M56: Yes | N56: ISO | O56: No
A57: PR.COV003.17 | B57: Monoline Building and Personal Property | C57: Commercial Property | D57: Business Personal Property | E57: Sprinkler Leakage | F57: Earthquake and Volcanic Eruption Endorsement | G57: CP 10 40 | H57: 02/19 | I57: Occurrence | J57: Optional | K57: First Party | L57: Grants Coverage | M57: Yes | N57: ISO | O57: No | AF57: Additional Coverage Forms: Human Services WRAP
A58: PR.COV003.18 | B58: Monoline Building and Personal Property | C58: Commercial Property | D58: Business Personal Property | E58: Spoilage | F58: Spoilage Coverage Endorsement | G58: CP 04 40 | H58: 12/20 | I58: Occurrence | J58: Optional | K58: First Party | L58: Grants Coverage | M58: Yes | N58: ISO | O58: No | AF58: Additional Coverage Forms: Equipment Breakdown Wrap, Human Services Wrap, Golf Course Wrap
A59: PR.COV003.19 | B59: Monoline Building and Personal Property | C59: Commercial Property | D59: Business Personal Property | E59: Utility Services | F59: Utility Services - Direct Damage Endorsement | G59: CP 04 17 | H59: 10/12 | I59: Occurrence | J59: Optional | K59: First Party | L59: Grants Coverage | M59: Yes | N59: ISO | O59: No | AF59: Additional Coverage Forms: Human Services WRAP
A60: PR.COV003.20 | B60: Monoline Building and Personal Property | C60: Commercial Property | D60: Business Personal Property | E60: Flood | F60: Flood Coverage Endorsement | G60: CP 10 65 | H60: 10/12 | I60: Occurrence | J60: Optional | K60: First Party | L60: Grants Coverage | N60: ISO | O60: No
A61: PR.COV003.21 | B61: Monoline Building and Personal Property | C61: Commercial Property | D61: Business Personal Property | E61: Brands And Labels | F61: Brands and Labels Endorsement | G61: CP 04 01 | H61: 10/00 | I61: Occurrence | J61: Optional | K61: First Party | L61: Grants Coverage | M61: Yes | N61: ISO | O61: No
A62: PR.COV003.22 | B62: Monoline Building and Personal Property | C62: Commercial Property | D62: Business Personal Property | E62: Green Upgrades | F62: Increased Cost of Loss and Related Expenses for Green Upgrades Endorsement | G62: CP 04 02 | H62: 10/12 | I62: Occurrence | J62: Optional | K62: First Party | L62: Grants Coverage | N62: ISO | O62: No
A63: PR.COV003.23 | B63: Monoline Building and Personal Property | C63: Commercial Property | D63: Business Personal Property | E63: Related Expenses | F63: Increased Cost of Loss and Related Expenses for Green Upgrades Endorsement | G63: CP 04 02 | H63: 10/12 | I63: Occurrence | J63: Optional | K63: First Party | L63: Grants Coverage | N63: ISO | O63: No
A64: PR.COV003.24 | B64: Monoline Building and Personal Property | C64: Commercial Property | D64: Business Personal Property | E64: Property Damage - Water Back-Up And Sump Overflow (Not Flood-Related) | F64: Water Back-up And Sump Overflow (Not Flood-Related) Endorsement | G64: CPE 06 96 | H64: 01/13 | I64: Occurrence | J64: Optional | K64: First Party | L64: Grants Coverage | N64: ISO | O64: No
A65: PR.COV003.25 | B65: Monoline Building and Personal Property | C65: Commercial Property | D65: Business Personal Property | E65: Power Outage | F65: Exclusion - Cyber Incident Property Endorsement | G65: CPE 10 75 | H65: 05/21 | I65: Occurrence | J65: Optional | K65: First Party | L65: Amends | N65: N/A | O65: Yes | AF65: Note - This Endorsement ties back to CP0440, HSB5000, CPT3500
A66: PR.COV003.26 | B66: Monoline Building and Personal Property | C66: Commercial Property | D66: Business Personal Property | E66: Public Safety Service Charges | F66: Universal Wrap | G66: CPT 90 99 | H66: 01/13 | I66: Occurrence | J66: Optional | K66: First Party | L66: Amends | N66: N/A | O66: Yes | AF66: Additional Coverage Forms: Elite Universal Wrap, Human Services Wrap
A67: PR.COV003.27 | B67: Monoline Building and Personal Property | C67: Commercial Property | D67: Business Personal Property | E67: Fine Arts At Described Premises | F67: Universal Wrap | G67: CPT 90 99 | H67: 01/13 | I67: Occurrence | J67: Optional | K67: First Party | L67: Amends | N67: N/A | O67: Yes | AF67: Additional Coverage Forms: Elite Universal Wrap, Human Services Wrap
A68: PR.COV003.28 | B68: Monoline Building and Personal Property | C68: Commercial Property | D68: Business Personal Property | E68: Fire Extinguisher Recharge | F68: Universal Wrap | G68: CPT 90 99 | H68: 01/13 | I68: Occurrence | J68: Optional | K68: First Party | L68: Amends | N68: N/A | O68: Yes | AF68: Additional Coverage Forms: Elite Universal Wrap, Human Services Wrap
A69: PR.COV003.29 | B69: Monoline Building and Personal Property | C69: Commercial Property | D69: Business Personal Property | E69: Accounts Receivable (Other Than Electronic Data) | F69: Universal Wrap | G69: CPT 90 99 | H69: 01/13 | I69: Occurrence | J69: Optional | K69: First Party | L69: Grants Coverage | N69: N/A | O69: Yes | AF69: Additional Coverage Forms: Elite Universal Wrap, Human Services Wrap, Golf Course Wrap
A70: PR.COV003.30 | B70: Monoline Building and Personal Property | C70: Commercial Property | D70: Business Personal Property | E70: Landlord Furnishings | F70: Universal Wrap | G70: CPT 90 99 | H70: 01/13 | I70: Occurrence | J70: Optional | K70: First Party | L70: Grants Coverage | N70: N/A | O70: Yes | AF70: Additional Coverage Forms: Elite Universal Wrap
A71: PR.COV003.31 | B71: Monoline Building and Personal Property | C71: Commercial Property | D71: Business Personal Property | E71: Theft Of Building Materials | F71: Universal Wrap | G71: CPT 90 99 | H71: 01/13 | I71: Occurrence | J71: Optional | K71: First Party | L71: Grants Coverage | N71: N/A | O71: Yes | AF71: Additional Coverage Forms: Universal Wrap Elite Universal Wrap
A72: PR.COV003.32 | B72: Monoline Building and Personal Property | C72: Commercial Property | D72: Business Personal Property | E72: Removal Of Property To Prevent A Loss | F72: Universal Wrap | G72: CPT 90 99 | H72: 01/13 | I72: Occurrence | J72: Optional | K72: First Party | L72: Grants Coverage | N72: N/A | O72: Yes
A73: PR.COV003.33 | B73: Monoline Building and Personal Property | C73: Commercial Property | D73: Business Personal Property | E73: Security After Loss | F73: Elite Universal Wrap | G73: CPT 79 99 | H73: 01/13 | I73: Occurrence | J73: Optional | K73: First Party | L73: Grants Coverage | N73: N/A | O73: Yes
A74: PR.COV003.34 | B74: Monoline Building and Personal Property | C74: Commercial Property | D74: Business Personal Property | E74: Property At Any Fair, Trade Show Or Exhibition | F74: Universal Wrap | G74: CPT 90 99 | H74: 01/13 | I74: Occurrence | J74: Optional | K74: First Party | L74: Grants Coverage | N74: N/A | O74: Yes | AF74: Additional Coverage Forms: Universal Wrap, Elite Universal Wrap
A75: PR.COV003.35 | B75: Monoline Building and Personal Property | C75: Commercial Property | D75: Business Personal Property | E75: Automated External Defibrillators | F75: Human Services Wrap | G75: CPT 35 00 | H75: 11/20 | I75: Occurrence | J75: Optional | K75: First Party | L75: Grants Coverage | N75: N/A | O75: Yes
A76: PR.COV003.36 | B76: Monoline Building and Personal Property | C76: Commercial Property | D76: Business Personal Property | E76: Mobile Medical Equipment | F76: Human Services Wrap | G76: CPT 35 00 | H76: 11/20 | I76: Occurrence | J76: Optional | K76: First Party | L76: Grants Coverage | N76: N/A | O76: Yes
A77: PR.COV003.37 | B77: Monoline Building and Personal Property | C77: Commercial Property | D77: Business Personal Property | E77: Limited International Coverage | F77: Human Services Wrap | G77: CPT 35 00 | H77: 11/20 | I77: Occurrence | J77: Optional | K77: First Party | L77: Grants Coverage | N77: N/A | O77: Yes
A78: PR.COV003.38 | B78: Monoline Building and Personal Property | C78: Commercial Property | D78: Business Personal Property | E78: Builders’ Machinery, Tools And Equipment | F78: Human Services Wrap | G78: CPT 35 00 | H78: 11/20 | I78: Occurrence | J78: Optional | K78: First Party | L78: Grants Coverage | N78: N/A | O78: Yes
A79: PR.COV003.39 | B79: Monoline Building and Personal Property | C79: Commercial Property | D79: Business Personal Property | E79: Claim Data Or Inventory Expense | F79: Human Services Wrap | G79: CPT 35 00 | H79: 11/20 | I79: Occurrence | J79: Optional | K79: First Party | L79: Grants Coverage | N79: N/A | O79: Yes | AF79: Additional Coverage Forms: Golf Course Wrap
A80: PR.COV003.40 | B80: Monoline Building and Personal Property | C80: Commercial Property | D80: Business Personal Property | E80: Valuation Of Donated Stock | F80: Human Services Wrap | G80: CPT 35 00 | H80: 11/20 | I80: Occurrence | J80: Optional | K80: First Party | L80: Grants Coverage | N80: N/A | O80: Yes
A81: PR.COV003.41 | B81: Monoline Building and Personal Property | C81: Commercial Property | D81: Business Personal Property | E81: Employee, Volunteer And Your Portable Tools | F81: Human Services Wrap | G81: CPT 35 00 | H81: 11/20 | I81: Occurrence | J81: Optional | K81: First Party | L81: Grants Coverage | N81: N/A | O81: Yes
A82: PR.COV003.42 | B82: Monoline Building and Personal Property | C82: Commercial Property | D82: Business Personal Property | E82: Deferred Payments | F82: Golf Course Property Wrap | G82: CPT 48 00 | H82: 04/21 | I82: Occurrence | J82: Optional | K82: First Party | L82: Grants Coverage | N82: N/A | O82: Yes
A83: PR.COV003.43 | B83: Monoline Building and Personal Property | C83: Commercial Property | D83: Business Personal Property | E83: Employee Tools | F83: Contractor and Services WRAP | G83: CPT 55 00 | H83: 01/13 | I83: Occurrence | J83: Optional | K83: First Party | L83: Amends | N83: N/A | O83: Yes | AF83: Additional Coverage Forms: Universal Wrap
A84: PR.COV003.44 | B84: Monoline Building and Personal Property | C84: Commercial Property | D84: Business Personal Property | E84: Installation - Jobsites | F84: Contractor and Services WRAP | G84: CPT 55 00 | H84: 01/13 | I84: Occurrence | J84: Optional | K84: First Party | L84: Amends | N84: N/A | O84: Yes | AF84: Additional Coverage Forms: Universal Wrap
A85: PR.COV003.45 | B85: Monoline Building and Personal Property | C85: Commercial Property | D85: Business Personal Property | E85: Contract Penalty Costs | F85: Elite Universal Wrap | G85: CPT 79 99 | H85: 01/13 | I85: Occurrence | J85: Optional | K85: First Party | L85: Grants Coverage | N85: N/A | O85: Yes
A86: PR.COV003.46 | B86: Monoline Building and Personal Property | C86: Commercial Property | D86: Business Personal Property | E86: Consequential Damage | F86: Golf Course Property Wrap | G86: CPT 48 00 | H86: 04/21 | I86: Occurrence | J86: Optional | K86: First Party | L86: Grants Coverage | N86: N/A | O86: Yes
A87: PR.COV003.47 | B87: Monoline Building and Personal Property | C87: Commercial Property | D87: Business Personal Property | E87: Theft Of Telephone Or Dataline Services | F87: Golf Course Property Wrap | G87: CPT 48 00 | H87: 04/21 | I87: Occurrence | J87: Optional | K87: First Party | L87: Grants Coverage | N87: N/A | O87: Yes
A88: PR.COV004.0 | B88: Monoline Building and Personal Property | C88: Commercial Property | D88: Personal Property of Others | F88: Building and Personal Property | G88: CP 00 10 | H88: 06/07 | I88: Occurrence | J88: Mandatory | K88: First Party | L88: Grants Coverage | M88: Yes | N88: ISO | O88: No
A89: PRCOV004.1 | B89: Monoline Building and Personal Property | C89: Commercial Property | D89: Personal Property of Others | E89: Preservation Of Property | F89: Building and Personal Property | G89: CP 00 10 | H89: 06/07 | I89: Occurrence | J89: Optional | K89: First Party | L89: Broadens | N89: ISO | O89: No
A90: PRCOV004.2 | B90: Monoline Building and Personal Property | C90: Commercial Property | D90: Personal Property of Others | E90: Outdoor Signs | F90: Building and Personal Property | G90: CP 00 10 | H90: 06/07 | I90: Occurrence | J90: Optional | K90: First Party | L90: Broadens | N90: ISO | O90: No | AF90: Additional Coverage Forms: Outdoor Signs Endorsement, Human Services Wrap
A91: PRCOV004.3 | B91: Monoline Building and Personal Property | C91: Commercial Property | D91: Personal Property of Others | E91: Property Off-Premises | F91: Building and Personal Property | G91: CP 00 10 | H91: 06/07 | I91: Occurrence | J91: Optional | K91: First Party | L91: Broadens | N91: ISO | O91: No | AF91: Additional Coverage Forms: Universal Wrap
A92: PRCOV004.4 | B92: Monoline Building and Personal Property | C92: Commercial Property | D92: Personal Property of Others | E92: Debris Removal | F92: Building and Personal Property | G92: CP 00 10 | H92: 06/07 | I92: Occurrence | J92: Optional | K92: First Party | L92: Broadens | N92: ISO | O92: No
A93: PRCOV004.5 | B93: Monoline Building and Personal Property | C93: Commercial Property | D93: Personal Property of Others | E93: Fire Department Service Charge | F93: Building and Personal Property | G93: CP 00 10 | H93: 06/07 | I93: Occurrence | J93: Optional | K93: First Party | L93: Broadens | N93: ISO | O93: No
A94: PRCOV004.6 | B94: Monoline Building and Personal Property | C94: Commercial Property | D94: Personal Property of Others | E94: Earthquake | F94: Earthquake and Volcanic Eruption Endorsement | G94: CP 10 40 | H94: 02/19 | I94: Occurrence | J94: Optional | K94: First Party | L94: Grants Coverage | M94: Yes | N94: ISO | O94: No
A95: PRCOV004.7 | B95: Monoline Building and Personal Property | C95: Commercial Property | D95: Personal Property of Others | E95: Volcanic Eruption | F95: Earthquake and Volcanic Eruption Endorsement | G95: CP 10 40 | H95: 02/19 | I95: Occurrence | J95: Optional | K95: First Party | L95: Grants Coverage | M95: Yes | N95: ISO | O95: No
A96: PRCOV004.8 | B96: Monoline Building and Personal Property | C96: Commercial Property | D96: Personal Property of Others | E96: Sprinkler Leakage | F96: Earthquake and Volcanic Eruption Endorsement | G96: CP 10 40 | H96: 02/19 | I96: Occurrence | J96: Optional | K96: First Party | L96: Grants Coverage | M96: Yes | N96: ISO | O96: No | AF96: Additional Coverage Forms: Human Services Wrap
A97: PRCOV004.9 | B97: Monoline Building and Personal Property | C97: Commercial Property | D97: Personal Property of Others | E97: Utility Services | F97: Utility Services - Direct Damage Endorsement | G97: CP 04 17 | H97: 10/12 | I97: Occurrence | J97: Optional | K97: First Party | L97: Grants Coverage | M97: Yes | N97: ISO | O97: No | AF97: Additional Coverage Forms: Human Services WRAP
A98: PRCOV004.10 | B98: Monoline Building and Personal Property | C98: Commercial Property | D98: Personal Property of Others | E98: Flood | F98: Flood Coverage Endorsement | G98: CP 10 65 | H98: 10/12 | I98: Occurrence | J98: Optional | K98: First Party | L98: Grants Coverage | N98: ISO | O98: No
A99: PRCOV004.11 | B99: Monoline Building and Personal Property | C99: Commercial Property | D99: Personal Property of Others | E99: Property Damage - Water Back-Up And Sump Overflow (Not Flood-Related) | F99: Water Back-up And Sump Overflow (Not Flood-Related) Endorsement | G99: CPE 06 96 | H99: 01/13 | I99: Occurrence | J99: Optional | K99: First Party | L99: Grants Coverage | N99: ISO | O99: No
A100: PRCOV004.12 | B100: Monoline Building and Personal Property | C100: Commercial Property | D100: Personal Property of Others | E100: Public Safety Service Charges | F100: Universal Wrap | G100: CPT 90 99 | H100: 01/13 | I100: Occurrence | J100: Optional | K100: First Party | L100: Amends | N100: N/A | O100: Yes | AF100: Additional Coverage Forms: Elite Universal Wrap, Human Services Wrap
A101: PRCOV004.13 | B101: Monoline Building and Personal Property | C101: Commercial Property | D101: Personal Property of Others | E101: Client Property - Theft By Employee | F101: Inn Wrap | G101: CPT 20 00 | H101: 11/20 | I101: Occurrence | J101: Optional | K101: First Party | L101: Grants Coverage | N101: N/A | O101: Yes | AF101: Additional Coverage Forms: Elite Universal Wrap, Human Services Wrap, Contractor Wrap, Green Industry Contractor Wrap
...

Sheet Property Forms Usage
A1: Form Type | B1: Form Number | C1: Form Name | D1: Category | E1: Proprietary or ISO | F1: Count of Forms | H1: PCM? | I1: Owner | J1: Comments | K1: Complete? | L1: Prop Or ISO | M1: PCM?
A3: PR | B3: CP 0090 0788 | C3: COMMERCIAL PROPERTY CONDITIONS | D3: POLICY CONDITIONS | E3: ISO | F3: 30914 | H3: N/A | I3: Tulio | L3: ISO | M3: N/A
A4: PR | B4: CP 0140 0706 | C4: EXCLUSION OF LOSS DUE TO VIRUS OR BACTERIA | D4: EXCLUSION | E4: ISO | F4: 30914 | H4: N/A | I4: Sal | L4: Proprietary | M4: ?
A5: PR | B5: CP 1032 0808 | C5: WATER EXCLUSION ENDORSEMENT | D5: EXCLUSION | E5: ISO | F5: 30913 | H5: N/A | I5: Sal | M5: X
A6: PR | B6: CP 1030 0607 | C6: CAUSES OF LOSS – SPECIAL FORM | D6: EXCLUSION | E6: ISO | F6: 30882 | H6: N/A
A7: PR | B7: CP 0010 0607 | C7: BUILDING & PERSONAL PROPERTY COVERAGE | D7: BASE COVERAGE FORM | E7: ISO | F7: 30859 | H7: X | I7: Tulio
A8: PR | B8: CPE 0100 2105 | C8: COMPUTER AMENDATORY | D8: ENDORSEMENT | E8: Proprietary | F8: 30847 | H8: X | I8: Sal
A9: PR | B9: CPE 1075 2105 | C9: EXCLUSION – CYBER INCIDENTS PROPERTY | D9: EXCLUSION | E9: Proprietary | F9: 30847 | H9: ? | I9: Sal | J9: **I believe this grants back: Spoiler Coverage (Power Outage) & Computer Fraud
A10: PR | B10: CPT 9000 1301 | C10: UNIVERSAL WRAP SCHEDULE | D10: POLICY CONDITIONS | E10: Proprietary | F10: 27599 | H10: N/A | I10: Sal | J10: **Just lists out limits that are being amended
A11: PR | B11: CPT 9099 1301 | C11: UNIVERSAL WRAP COVERAGE FORM | D11: WRAP | E11: Proprietary | F11: 27599 | H11: X | I11: Sal
A12: PR | B12: HSB 5000 1301 | C12: EQUIPMENT BREAKDOWN WRAP CAUSES OF LOSS - BREAKDOWN | D12: OTHER COVERAGE FORM | E12: Proprietary | F12: 27423 | H12: X | I12: Sal
A13: PR | B13: CP 1504 0607 | C13: DISCRETIONARY PAYROLL EXPENSE | D13: POLICY CONDITIONS | E13: ISO | F13: 23128 | H13: X | I13: Sal | J13: **Schedules type of employees/max # of days
A14: PR | B14: CP 0030 0607 | C14: BUSINESS INCOME AND EXTRA EXPENSE COVERAGE | D14: BASE COVERAGE FORM | E14: ISO | F14: 23112 | H14: X | I14: Rohit
A15: PR | B15: CPE 0696 1301 | C15: Water Back-up And Sump Overflow (Not Flood-Related) | D15: OTHER COVERAGE FORM | E15: Proprietary | F15: 20241 | H15: X | I15: Sal
A16: PR | B16: CPE 1555 1301 | C16: BUSINESS INCOME – ACTUAL LOSS SUSTAINED | D16: POLICY CONDITIONS | E16: Proprietary | F16: 18447 | H16: N/A | I16: Sal | J16: This form doesn't add coverage, it modifies the terms of coverage under Business Income (SS)
A17: PR | B17: CP 1556 0607 | C17: BUSINESS INCOME CHANGES – BEGINNING OF THE PERIOD OF RESTORATION | D17: ENDORSEMENT | E17: ISO | F17: 14730 | H17: N/A | I17: Sal
A18: PR | B18: CPT 5500 1301 | C18: CONTRACTOR AND SERVICES WRAP | D18: WRAP | E18: Proprietary | F18: 9311 | H18: X | I18: Sal
A19: PR | B19: CP 0113 1002 | C19: WISCONSIN CHANGES | D19: ENDORSEMENT | E19: ISO | F19: 8452 | H19: N/A | I19: Rohit
A20: PR | B20: CP 1550 1185 | C20: RADIO OR TELEVISION ANTENNAS – BUSINESS INCOME OR EXTRA EXPENSE | D20: ENDORSEMENT | E20: ISO | F20: 7819 | H20: N/A | I20: Rohit
A21: PR | B21: CP 1218 0607 | C21: LOSS PAYABLE PROVISIONS | D21: POLICY CONDITIONS | E21: ISO | F21: 6466 | H21: N/A | I21: Rohit
A22: PR | B22: CP 0108 0520 | C22: MINNESOTA CHANGES | D22: POLICY CONDITIONS | E22: ISO | F22: 4657 | H22: ? | J22: Can't find this form (SS)
A23: PR | B23: CP 0150 1000 | C23: MINNESOTA CHANGES – REPLACEMENT COST PERSONAL PROPERTY | D23: POLICY CONDITIONS | E23: ISO | F23: 4116 | H23: N/A | J23: Updates existing coverage
A24: PR | B24: CP 0149 0607 | C24: ILLINOIS CHANGES – ARTIFICIALLY GENERATED ELECTRICAL CURRENT EXCLUSION | D24: EXCLUSION | E24: ISO | F24: 2565 | H24: N/A
A25: PR | B25: CP 0157 0918 | C25: MINNESOTA CHANGES - COINSURANCE | D25: POLICY CONDITIONS | E25: ISO | F25: 2386 | H25: N/A
A26: PR | B26: CP 0128 0700 | C26: MISSOURI – CALCULATION OF ADDITIONAL PREMIUM | D26: ENDORSEMENT | E26: ISO | F26: 2331 | H26: N/A | I26: Tulio
A27: PR | B27: CP 1270 0996 | C27: JOINT OR DISPUTED LOSS AGREEMENT | D27: POLICY CONDITIONS | E27: ISO | F27: 2327 | H27: N/A | I27: Sal | J27: * Requires a CP + Builders' Risk policy by different insurers - describes terms of how a loss to covered property will be payed
A28: PR | B28: CPE 1036 1305 | C28: LIMITATIONS ON COVERAGE FOR ROOF SURFACING | D28: POLICY CONDITIONS | E28: Proprietary | F28: 2278 | H28: N/A | I28: Sal | J28: **This restricts coverage caused by wind/hail to the roof of the building
A29: PR | B29: CP 0166 0900 | C29: KENTUCKY CHANGES | D29: ENDORSEMENT | E29: ISO | F29: 2253 | H29: N/A | I29: Tulio
A30: PR | B30: CP 1040 0899 | C30: EARTHQUAKE AND VOLCANIC ERUPTION ENDORSEMENT | D30: ENDORSEMENT | E30: ISO | F30: 2248 | H30: X | I30: Tulio
A31: PR | B31: CP 0132 0120 | C31: ARIZONA CHANGES | D31: ENDORSEMENT | E31: ISO | F31: 2223 | H31: N/A | I31: Tulio
A32: PR | B32: CP 0146 0894 | C32: ARIZONA CHANGES | D32: ENDORSEMENT | E32: ISO | F32: 2195 | H32: ? | I32: Tulio | J32: This removes Fire Dept. Service Charge… from ALL Property Coverages
A33: PR | B33: CPE 0200 1301 | C33: GREENHOUSE VALUATION AMENDMENT | D33: POLICY CONDITIONS | E33: Proprietary | F33: 2193 | H33: N/A | I33: Sal | J33: **This restricts certain coverage and terms applicable to Greenhouses only (ex: ACV doesn't apply, Coinsurance applies, terms to be covered are added - 'temp must be > 40 degrees)
A34: PR | B34: CPT 7999 1301 | C34: ELITE UNIVERSAL WRAP COVERAGE FORM | D34: WRAP | E34: Proprietary | F34: 1962 | H34: X | I34: Sal
A35: PR | B35: CP 0120 0421 | C35: MICHIGAN CHANGES | D35: ENDORSEMENT | E35: ISO | F35: 1910 | H35: N/A | I35: Tulio
A36: PR | B36: CPT 7900 1301 | C36: MICHIGAN CHANGES | D36: ENDORSEMENT | E36: Proprietary | F36: 1830 | H36: N/A | I36: Tulio | J36: This is just a schedule for the Michigan Wrapper
A37: PR | B37: CPE 2411 1106 | C37: MISSOURI CHANGES – LOSS NOTICE REQUIREMENTS | D37: OTHER (Notices, Dec, etc.) | E37: Proprietary | F37: 1823 | H37: N/A
A38: PR | B38: CP 1221 0208 | C38: LOSS PAYABLE PROVISIONS - MINNESOTA | D38: POLICY CONDITIONS | E38: ISO | F38: 1451 | H38: N/A
A39: PR | B39: CP 0114 1115 | C39: NORTH DAKOTA CHANGES | D39: ENDORSEMENT | E39: ISO | F39: 1400 | H39: N/A | I39: Tulio | J39: Valued Policies 2. might be good to double check with Rebecca
A40: PR | B40: CPT 4500 1301 | C40: RESTAURANT WRAP | D40: WRAP | E40: Proprietary | F40: 1291 | H40: X | I40: Sal
A41: PR | B41: CP 0152 0796 | C41: INDIANA CHANGES – RIGHTS OF RECOVERY | D41: ENDORSEMENT | E41: ISO | F41: 1200 | H41: N/A | I41: Tulio
A42: PR | B42: PLI 0963 1301 | C42: INDIANA - NOTICE REGARDING MINE SUBSIDENCE COVERAGE | D42: OTHER (Notices, Dec, etc.) | E42: Proprietary | F42: 1188 | H42: ? | J42: Can't find this form - does this add coverage for IN?
A43: PR | B43: CPT 3500 2011 | C43: HUMAN SERVICES PROPERTY WRAP | D43: WRAP | E43: Proprietary | F43: 1161 | H43: X | I43: Sal
A44: PR | B44: CP 0120 0918 | C44: MICHIGAN CHANGES | D44: ENDORSEMENT | E44: ISO | F44: 1020 | H44: N/A | I44: Tulio
A45: PR | B45: CP 1211 1000 | C45: BURGLARY AND ROBBERY PROTECTIVE SAFEGUARDS | D45: POLICY CONDITIONS | E45: ISO | F45: 987 | H45: N/A | I45: Tulio | J45: This is a provision, that the insured must maintain alarm systems
A46: PR | B46: CPT 7550 1301 | C46: ELITE CONTRACTOR WRAP | D46: WRAP | E46: Proprietary | F46: 942 | H46: N/A | I46: Sal
A47: PR | B47: CP 1910 0695 | C47: YOUR BUSINESS PERSONAL PROPERTY – SEPARATION OF COVERAGE | D47: ENDORSEMENT | E47: ISO | F47: 895 | H47: N/A | I47: Tulio
A48: PR | B48: CPT 6000 1301 | C48: MANUFACTURER WRAP | D48: WRAP | E48: Proprietary | F48: 891 | H48: X | I48: Sal | J48: Only one new coverage, the rest are amended or limits are modified (SS)
A49: PR | B49: CP 0320 1092 | C49: MULTIPLE DEDUCTIBLE FORM | D49: ENDORSEMENT | E49: ISO | F49: 874 | H49: ? | I49: Tulio | J49: Rebecca, what do we do in this instance?
A50: PR | B50: CP 0440 0607 | C50: SPOILAGE COVERAGE | D50: ENDORSEMENT | E50: ISO | F50: 729 | H50: X | I50: Tulio
A51: PR | B51: CP 1410 0695 | C51: ADDITIONAL COVERED PROPERTY | D51: ENDORSEMENT | E51: ISO | F51: 682 | H51: X | I51: Tulio
A52: PR | B52: CP 0321 0607 | C52: WINDSTORM OR HAIL PERCENTAGE DEDUCTIBLE | D52: ENDORSEMENT | E52: ISO | F52: 600 | H52: X | I52: Tulio
A53: PR | B53: CPT 7610 1301 | C53: ELITE MANUFACTURING WRAP | D53: WRAP | E53: Proprietary | F53: 474 | H53: N/A | I53: Sal
A54: PR | B54: CP 0405 0402 | C54: ORDINANCE OR LAW COVERAGE | D54: ENDORSEMENT | E54: ISO | F54: 464 | H54: X | I54: Tulio
A55: PR | B55: HEE 3435 1301 | C55: BREAKDOWN COVERAGE MODIFICATION SCHEDULE – METALS and MANUFACTURING | D55: ENDORSEMENT | E55: Proprietary | F55: 441 | H55: N/A | I55: Rohit
A56: PR | B56: CPT 2000 2011 | C56: INN WRAP | D56: WRAP | E56: Proprietary | F56: 416 | H56: X | I56: Sal
A57: PR | B57: CP 1219 0607 | C57: ADDITIONAL INSURED – BUILDING OWNER | D57: ENDORSEMENT | E57: ISO | F57: 389 | H57: N/A | I57: Tulio
A58: PR | B58: CP 1545 0607 | C58: UTILITY SERVICES – TIME ELEMENT | D58: ENDORSEMENT | E58: ISO | F58: 372 | H58: X | I58: Tulio
A59: PR | B59: CP 1440 0607 | C59: OUTDOOR SIGNS | D59: ENDORSEMENT | E59: ISO | F59: 352 | H59: X | I59: Tulio
A60: PR | B60: CPE 0431 1301 | C60: FOOD CONTAMINATION | D60: ENDORSEMENT | E60: Proprietary | F60: 290 | H60: X | I60: Rohit | J60: This coverage is applicable to BI and BIEE. Should we include them under BI and BIEE
A61: PR | B61: CP 0417 0607 | C61: UTILITY SERVICES – DIRECT DAMAGE | D61: ENDORSEMENT | E61: ISO | F61: 245 | H61: X | I61: Tulio
A62: PR | B62: CP 0101 0619 | C62: KANSAS CHANGES | D62: ENDORSEMENT | E62: ISO | F62: 241 | H62: N/A | I62: Tulio
A63: PR | B63: CPE 4040 2104 | C63: TREES - EXPANDED CAUSES OF LOSS | D63: ENDORSEMENT | E63: Proprietary | F63: 231 | H63: ? | I63: Rohit | J63: Similar to CPE 0431 1301
A64: PR | B64: CPT 7450 1301 | C64: ELITE RETAIL AND WHOLESALE WRAP | D64: WRAP | E64: Proprietary | F64: 231 | H64: N/A | I64: Sal
A65: PR | B65: CPE 4060 2104 | C65: TREES SHRUBS AND PLANTS SUPPLEMENTAL DEBRIS REMOVAL | D65: ENDORSEMENT | E65: Proprietary | F65: 220 | H65: N/A | I65: Rohit | J65: COMMERCIAL PROPERTY and STANDARD PROPERTY
A66: PR | B66: CPE 0474 1301 | C66: ADDITIONAL INTEREST ENDORSEMENT | D66: ENDORSEMENT | E66: Proprietary | F66: 201 | H66: N/A | I66: Rohit
A67: PR | B67: CP 1420 0788 | C67: ADDITIONAL PROPERTY NOT COVERED | D67: EXCLUSION | E67: ISO | F67: 186 | H67: N/A | I67: Sal | J67: This looks like a schedule of property not covered? If so, I don't think this applies
A68: PR | B68: CPT 4800 2104 | C68: GOLF COURSE PROPERTY WRAP | D68: WRAP | E68: Proprietary | F68: 184 | H68: X | I68: Sal
A69: PR | B69: CPT 5506 1301 | C69: GREEN INDUSTRY CONTRACTOR WRAP | D69: WRAP | E69: Proprietary | F69: 162 | H69: X | I69: Sal
A70: PR | B70: CPE 9000 1102 | C70: DOMESTIC ANIMAL BAILEE COVERAGE | D70: OTHER COVERAGE FORM | E70: Proprietary | F70: 152 | H70: X | I70: Sal
A71: PR | B71: CP 0438 0607 | C71: FUNCTIONAL BUILDING VALUATION | D71: ENDORSEMENT | E71: ISO | F71: 149 | H71: X | I71: Sal
A72: PR | B72: HEE 1030 1301 | C72: BREAKDOWN COVERAGE MODIFICATION SCHEDULE – PRINTING INDUSTRY | D72: ENDORSEMENT | E72: Proprietary | F72: 145 | H72: N/A | I72: Rohit
A73: PR | B73: HEE 1004 1301 | C73: EQUIPMENT BREAKDOWN COVERAGE MODIFICATION SCHEDULE | D73: ENDORSEMENT | E73: Proprietary | F73: 141 | H73: N/A | I73: Sal | J73: Just a schedule
A74: PR | B74: CP 1230 0695 | C74: PEAK SEASON LIMIT OF INSURANCE | D74: ENDORSEMENT | E74: ISO | F74: 134 | H74: N/A | I74: Sal | J74: Sub-limits scheduled property
A75: PR | B75: CPT 7905 1301 | C75: ELITE UNIVERSAL WRAP SCHEDULE | D75: OTHER (Notices, Dec, etc.) | E75: Proprietary | F75: 132 | H75: N/A | I75: Sal
A76: PR | B76: CP 0017 0607 | C76: CONDOMINUM ASSOCIATION COVERAGE | D76: BASE COVERAGE FORM | E76: ISO | F76: 131 | H76: X | I76: Tulio
A77: PR | B77: CPE 6010 1908 | C77: TANK LEAKAGE AND PRODUCT CONTAMINATION | D77: ENDORSEMENT | E77: Proprietary | F77: 128 | H77: X | I77: Rohit
A78: PR | B78: CPE 6000 1908 | C78: BEVERAGE MANUFACTURING COVERAGE ENDORSEMENT | D78: ENDORSEMENT | E78: Proprietary | F78: 125 | H78: N/A | I78: Rohit
A79: PR | B79: CP 0020 0607 | C79: BUILDERS RISK COVERAGE | D79: BASE COVERAGE FORM | E79: ISO | F79: 120 | H79: X | I79: Tulio
A80: PR | B80: CP 0050 0607 | C80: EXTRA EXPENSE COVERAGE | D80: BASE COVERAGE FORM | E80: ISO | F80: 78 | H80: X | I80: Rohit
A81: PR | B81: CPE 0018 1301 | C81: CONDOMINIUM COMMERCIAL UNIT-OWNERS COVERAGE AMENDMENT | D81: ENDORSEMENT | E81: Proprietary | F81: 71
A82: PR | B82: CPE 0100 1301 | C82: COMPUTER AMENDATORY | D82: OTHER COVERAGE FORM | E82: Proprietary | F82: 67 | H82: X | I82: Sal
A83: PR | B83: CP 0197 1105 | C83: IOWA – STANDARD FIRE POLICY PROVISIONS | D83: ENDORSEMENT | E83: ISO | F83: 64 | H83: N/A | I83: Sal | J83: I believe this is just a notice - didn't find coverage
A84: PR | B84: IL1201 1185 - PR | C84: Policy Changes | D84: OTHER (Notices, Dec, etc.) | F84: 59 | H84: N/A
A85: PR | B85: CPT 7510 1301 | C85: ELITE SERVICES WRAP | D85: WRAP | E85: Proprietary | F85: 48 | H85: N/A | I85: Sal
A86: PR | B86: CPT 7800 2104 | C86: ELITE GOLF COURSE PROPERTY WRAP | D86: WRAP | E86: Proprietary | F86: 46 | H86: N/A | I86: Sal
A87: PR | B87: CP 1010 0607 | C87: CAUSES OF LOSS – BASIC FORM | D87: CAUSES OF LOSS | E87: ISO | F87: 45 | H87: N/A
A88: PR | B88: CP 0040 0607 | C88: LEGAL LIABILITY COVERAGE | D88: BASE COVERAGE FORM | E88: ISO | F88: 44 | H88: X | I88: Tulio
A89: PR | B89: CPE 0606 1001 | C89: HEPATITIS A COVERAGE | D89: ENDORSEMENT | E89: Proprietary | F89: 44 | J89: *Business Income - A.5.Additional Coverages: Adds Hep A Coverage
A90: PR | B90: CP 1020 0607 | C90: CAUSES OF LOSS – BROAD FORM | D90: CAUSES OF LOSS | E90: ISO | F90: 43 | H90: N/A
A91: PR | B91: CP 1113 0695 | C91: BUILDERS RISK RENOVATIONS | D91: ENDORSEMENT | E91: ISO | F91: 43 | H91: X | I91: Sal
A92: PR | B92: CP 1415 0788 | C92: ADDITIONAL BUILDING PROPERTY | D92: ENDORSEMENT | E92: ISO | F92: 42 | H92: N/A | I92: Sal | J92: **Is this old? Is this needed using the the new 1020 Builders Risk? This is just a schedule of buildings that are covered.
A93: PR | B93: CP 1310 0402 | C93: VALUE REPORTING FORM | D93: POLICY CONDITIONS | E93: ISO | F93: 41
A94: PR | B94: CP 0415 1000 | C94: DEBRIS REMOVAL ADDITIONAL INSURANCE | D94: POLICY CONDITIONS | E94: ISO | F94: 40 | J94: *Increases Limits at specified locations
A95: PR | B95: CPT 7455 1301 | C95: ELITE GROCERS VALUE WRAP | D95: WRAP | E95: Proprietary | F95: 40 | H95: N/A | I95: Sal
A96: PR | B96: CPE 1093 1305 | C96: ROOF SURFACING – ACTUAL CASH VALUE LOSS SETTLEMENT | D96: ENDORSEMENT | E96: Proprietary | F96: 37 | J96: *Roof Surfacing ACV Coverage?
A97: PR | B97: CP 9930 0695 | C97: MANUFACTURER'S SELLING PRICE FINISHED "STOCK" ONLY | D97: ENDORSEMENT | E97: ISO | F97: 33 | H97: N/A | I97: Sal | J97: Policy Conditions
A98: PR | B98: CP 0418 0607 | C98: CONDOMINIUM COMMERCIAL UNIT-OWNERS OPTIONAL COVERAGES | D98: ENDORSEMENT | E98: ISO | F98: 32 | H98: X | I98: Tulio
A99: PR | B99: CP 1120 0607 | C99: BUILDERS RISK – COLLAPSE DURING CONSTRUCTION | D99: ENDORSEMENT | E99: ISO | F99: 32 | H99: X | I99: Sal | J99: * Adds Collapse to Builders Risk
A100: PR | B100: CP 1330 0607 | C100: AGRICULTURAL PRODUCTS STORAGE | D100: OTHER COVERAGE FORM | E100: ISO | F100: 30
A101: PR | B101: CP 0443 1005 | C101: MINNESOTA CHANGES – FUNCTIONAL BUILDING VALUATION | D101: ENDORSEMENT | E101: ISO | F101: 27 | H101: X | I101: Tulio
...

Sheet Coverage Summary
D1: Required | E1: Universal Wraps Include All Base Coverages | G1: Trade-Specific WRAPs Include Coverages From BPP & Universal/Elite
A2: ID | B2: Coverage | C2: Sub-Coverage | D2: Monoline Building and Personal Property | E2: Universal Coverages | F2: Elite Universal Coverages | G2: Inn Product Coverages | H2: Golf Course Coverages | I2: Human Services Coverages | J2: Restaurant Coverages | K2: Contractor and Services Coverages | L2: Green Industry Contractor Coverages | M2: Equipment Breakdown Coverages | N2: Tank Leakage Coverages | O2: Manufacturer Coverages
B3: Building | D3: X | E3: X | F3: X | G3: X | H3: X | I3: X | J3: X | K3: X | L3: X | M3: X | N3: X | O3: X
B4: Building | C4: Preservation of Property | D4: X | E4: X | F4: X | G4: X | H4: X | I4: X | J4: X | K4: X | L4: X | M4: X | N4: X | O4: X
B5: Building | C5: Outdoor Signs | D5: X | E5: X | F5: X | G5: X | H5: X | I5: X | J5: X | K5: X | L5: X | M5: X | N5: X | O5: X
B6: Building | C6: Newly Acquired or Constructed Property | D6: X | E6: X | F6: X | G6: X | H6: X | I6: X | J6: X | K6: X | L6: X | M6: X | N6: X | O6: X
B7: Building | C7: Increased Cost of Construction | D7: X | E7: X | F7: X | G7: X | H7: X | I7: X | J7: X | K7: X | L7: X | M7: X | N7: X | O7: X
B8: Building | C8: Debris Removal | D8: X | E8: X | F8: X | G8: X | H8: X | I8: X | J8: X | K8: X | L8: X | M8: X | N8: X | O8: X
B9: Building | C9: Fire Department Service Charge | D9: X | E9: X | F9: X | G9: X | H9: X | I9: X | J9: X | K9: X | L9: X | M9: X | N9: X | O9: X
B10: Building | C10: Public Safety Service Charges | E10: X | F10: X | G10: X | H10: X | I10: X | J10: X | K10: X | L10: X | M10: X | N10: X | O10: X
B11: Building | C11: Lock Replacement Due to Theft of Keys or Transmitters | E11: X | F11: X | G11: X | H11: X | I11: X | J11: X | K11: X | L11: X | M11: X | N11: X | O11: X
B12: Building | C12: Tenant Glass Breakage | E12: X | F12: X | G12: X | H12: X | I12: X | J12: X | K12: X | L12: X | M12: X | N12: X | O12: X
B13: Building | C13: Unscheduled Structures (Garages, Storage Buildings and Other Structures) | E13: X | F13: X | G13: X | H13: X | I13: X | J13: X | K13: X | L13: X | M13: X | N13: X | O13: X
B14: Building | C14: Tenant Building | E14: X | F14: X | G14: X | H14: X | I14: X | J14: X | K14: X | L14: X | M14: X | N14: X | O14: X
B15: Building | C15: Contract Penalty Costs | F15: X
B16: Building | C16: Realty Tax-Increased Assessment | F16: X
B17: Building | C17: Security After Loss | F17: X
B18: Building | C18: Claim Data or Inventory Expense | H18: X | I18: X
B19: Building | C19: Swimming Pools And Inground Sprinkler Systems | H19: X
B20: Business Personal Property | D20: X | E20: X | F20: X | G20: X | H20: X | I20: X | J20: X | K20: X | L20: X | M20: X | N20: X | O20: X
B21: Business Personal Property | C21: Preservation of Property | D21: X | E21: X | F21: X | G21: X | H21: X | I21: X | J21: X | K21: X | L21: X | M21: X | N21: X | O21: X
B22: Business Personal Property | C22: Outdoor Signs | D22: X | E22: X | F22: X | G22: X | H22: X | I22: X | J22: X | K22: X | L22: X | M22: X | N22: X | O22: X
B23: Business Personal Property | C23: Newly Acquired or Constructed Property | D23: X | E23: X | F23: X | G23: X | H23: X | I23: X | J23: X | K23: X | L23: X | M23: X | N23: X | O23: X
B24: Business Personal Property | C24: Electronic data | D24: X | E24: X | F24: X | G24: X | H24: X | I24: X | J24: X | K24: X | L24: X | M24: X | N24: X | O24: X
B25: Business Personal Property | C25: Personal Effects and Property of Others | D25: X | E25: X | F25: X | G25: X | H25: X | I25: X | J25: X | K25: X | L25: X | M25: X | N25: X | O25: X
B26: Business Personal Property | C26: Valuable Papers & Records (other than Electronic Data) | D26: X | E26: X | F26: X | G26: X | H26: X | I26: X | J26: X | K26: X | L26: X | M26: X | N26: X | O26: X
B27: Business Personal Property | C27: Property Off-Premises | D27: X | E27: X | F27: X | G27: X | H27: X | I27: X | J27: X | K27: X | L27: X | M27: X | N27: X | O27: X
B28: Business Personal Property | C28: Non-owned detached trailers | D28: X | E28: X | F28: X | G28: X | H28: X | I28: X | J28: X | K28: X | L28: X | M28: X | N28: X | O28: X
B29: Business Personal Property | C29: Debris Removal | D29: X | E29: X | F29: X | G29: X | H29: X | I29: X | J29: X | K29: X | L29: X | M29: X | N29: X | O29: X
B30: Business Personal Property | C30: Fire Department Service Charge | D30: X | E30: X | F30: X | G30: X | H30: X | I30: X | J30: X | K30: X | L30: X | M30: X | N30: X | O30: X
B31: Business Personal Property | C31: Public Safety Service Charges | E31: X | F31: X | G31: X | H31: X | I31: X | J31: X | K31: X | L31: X | M31: X | N31: X | O31: X
B32: Business Personal Property | C32: Fine Arts at Described Premises | E32: X | F32: X | G32: X | H32: X | I32: X | J32: X | K32: X | L32: X | M32: X | N32: X | O32: X
B33: Business Personal Property | C33: Fire Extinguisher Recharge | E33: X | F33: X | G33: X | H33: X | I33: X | J33: X | K33: X | L33: X | M33: X | N33: X | O33: X
B34: Business Personal Property | C34: Accounts Receivable (Other Than Electronic Data) | E34: X | F34: X | G34: X | H34: X | I34: X | J34: X | K34: X | L34: X | M34: X | N34: X | O34: X
B35: Business Personal Property | C35: Landlord Furnishings | E35: X | F35: X | G35: X | H35: X | I35: X | J35: X | K35: X | L35: X | M35: X | N35: X | O35: X
B36: Business Personal Property | C36: Theft of Building Materials | E36: X | F36: X | G36: X | H36: X | I36: X | J36: X | K36: X | L36: X | M36: X | N36: X | O36: X
B37: Business Personal Property | C37: Removal of Property To Prevent a Loss | E37: X | F37: X | G37: X | H37: X | I37: X | J37: X | K37: X | L37: X | M37: X | N37: X | O37: X
B38: Business Personal Property | C38: Security After Loss | F38: X | G38: X | H38: X | I38: X | J38: X | K38: X | L38: X | M38: X | N38: X | O38: X
B39: Business Personal Property | C39: Property at any Fair, Trade Show or Exhibition | E39: X | F39: X | G39: X | H39: X | I39: X | J39: X | K39: X | L39: X | M39: X | N39: X | O39: X
B40: Business Personal Property | C40: Automated External Defibrillators | I40: X
B41: Business Personal Property | C41: Mobile Medical Equipment | I41: X
B42: Business Personal Property | C42: Limited International Coverage | I42: X
B43: Business Personal Property | C43: Builders’ Machinery, Tools and Equipment | I43: X
B44: Business Personal Property | C44: Claim Data or Inventory Expense | I44: X
B45: Business Personal Property | C45: Valuation of Donated Stock | I45: X
B46: Business Personal Property | C46: Employee, Volunteer and Your Portable Tools | I46: X
B47: Business Personal Property | C47: Deferred Payments | H47: X
B48: Business Personal Property | C48: Employee Tools | K48: X
B49: Business Personal Property | C49: Installation - Jobsites | K49: X
B50: Business Personal Property | C50: Contract Penalty Costs | F50: X
B51: Business Personal Property | C51: Consequential Damage | H51: X
B52: Business Personal Property | C52: Theft of Telephone or Dataline Services | H52: X
B53: Personal Property of Others | D53: X | E53: X | F53: X | G53: X | H53: X | I53: X | J53: X | K53: X | L53: X | M53: X | N53: X | O53: X
B54: Personal Property of Others | C54: Preservation of Property | D54: X | E54: X | F54: X | G54: X | H54: X | I54: X | J54: X | K54: X | L54: X | M54: X | N54: X | O54: X
B55: Personal Property of Others | C55: Outdoor Signs | D55: X | E55: X | F55: X | G55: X | H55: X | I55: X | J55: X | K55: X | L55: X | M55: X | N55: X | O55: X
B56: Personal Property of Others | C56: Property Off-Premises | D56: X | E56: X | F56: X | G56: X | H56: X | I56: X | J56: X | K56: X | L56: X | M56: X | N56: X | O56: X
B57: Personal Property of Others | C57: Debris Removal | D57: X | E57: X | F57: X | G57: X | H57: X | I57: X | J57: X | K57: X | L57: X | M57: X | N57: X | O57: X
B58: Personal Property of Others | C58: Fire Department Service Charge | D58: X | E58: X | F58: X | G58: X | H58: X | I58: X | J58: X | K58: X | L58: X | M58: X | N58: X | O58: X
B59: Personal Property of Others | C59: Public Safety Service Charges | E59: X | F59: X | G59: X | H59: X | I59: X | J59: X | K59: X | L59: X | M59: X | N59: X | O59: X
B60: Personal Property of Others | C60: Client Property - Theft By Employee | G60: X | I60: X | J60: X | K60: X | L60: X
B61: Personal Property of Others | C61: Care, Custody or Control Other Than Theft | D61: X | E61: X | F61: X | G61: X | H61: X | I61: X | J61: X | K61: X | L61: X | M61: X | N61: X | O61: X
B62: Business Personal Property | C62: Removal of Property To Prevent a Loss | E62: X | F62: X | G62: X | H62: X | I62: X | J62: X | K62: X | L62: X | M62: X | N62: X | O62: X
B63: Business Personal Property | C63: Contract Penalty Costs | F63: X | G63: X | H63: X | I63: X | J63: X | K63: X | L63: X | M63: X | N63: X | O63: X
B64: Business Personal Property | C64: Security After Loss | F64: X | G64: X | H64: X | I64: X | J64: X | K64: X | L64: X | M64: X | N64: X | O64: X
B65: Business Personal Property | C65: Limited International Coverage | I65: X
B66: Business Personal Property | C66: Employee, Volunteer and Your Portable Tools | I66: X
B67: Business Personal Property | C67: Claim Data or Inventory Expense | I67: X
B68: Business Personal Property | C68: Personal Property of Golf Club Professionals | H68: X
C69: Personal Property of Members, Customers & Guests | H69: X
C70: Theft of Telephone or Dataline Services | H70: X
B71: Vehicles: Manufactured, processed, or warehoused | D71: X | E71: X | F71: X | G71: X | H71: X | I71: X | J71: X | K71: X | L71: X | M71: X | N71: X | O71: X
B72: Vehicles: Manufactured, processed, or warehoused | C72: Preservation of Property | D72: X | E72: X | F72: X | G72: X | H72: X | I72: X | J72: X | K72: X | L72: X | M72: X | N72: X | O72: X
B73: Vehicles: Manufactured, processed, or warehoused | C73: Property Off-Premises | D73: X | E73: X | F73: X | G73: X | H73: X | I73: X | J73: X | K73: X | L73: X | M73: X | N73: X | O73: X
B74: Vehicles: Manufactured, processed, or warehoused | C74: Debris Removal | D74: X | E74: X | F74: X | G74: X | H74: X | I74: X | J74: X | K74: X | L74: X | M74: X | N74: X | O74: X
B75: Vehicles: Manufactured, processed, or warehoused | C75: Fire Department Service Charge | D75: X | E75: X | F75: X | G75: X | H75: X | I75: X | J75: X | K75: X | L75: X | M75: X | N75: X | O75: X
B76: Business Personal Property | C76: Removal of Property To Prevent a Loss | E76: X | F76: X | G76: X | H76: X | I76: X | J76: X | K76: X | L76: X | M76: X | N76: X | O76: X
B77: Business Personal Property | C77: Contract Penalty Costs | F77: X
B78: Business Personal Property | C78: Security After Loss | F78: X
C79: Claim Data or Inventory Expense | I79: X
B80: Vehicles for sale (except autos) | D80: X | E80: X | F80: X | G80: X | H80: X | I80: X | J80: X | K80: X | L80: X | M80: X | N80: X | O80: X
B81: Vehicles for sale (except autos) | C81: Preservation of Property | D81: X | E81: X | F81: X | G81: X | H81: X | I81: X | J81: X | K81: X | L81: X | M81: X | N81: X | O81: X
B82: Vehicles for sale (except autos) | C82: Property Off-Premises | D82: X | E82: X | F82: X | G82: X | H82: X | I82: X | J82: X | K82: X | L82: X | M82: X | N82: X | O82: X
B83: Vehicles for sale (except autos) | C83: Debris Removal | D83: X | E83: X | F83: X | G83: X | H83: X | I83: X | J83: X | K83: X | L83: X | M83: X | N83: X | O83: X
B84: Vehicles for sale (except autos) | C84: Fire Department Service Charge | D84: X | E84: X | F84: X | G84: X | H84: X | I84: X | J84: X | K84: X | L84: X | M84: X | N84: X | O84: X
B85: Vehicles for sale (except autos) | C85: Removal of Property To Prevent a Loss | E85: X | F85: X | G85: X | H85: X | I85: X | J85: X | K85: X | L85: X | M85: X | N85: X | O85: X
B86: Business Personal Property | C86: Contract Penalty Costs | F86: X
B87: Business Personal Property | C87: Security After Loss | F87: X
C88: Claim Data or Inventory Expense | I88: X
B89: Rowboats or canoes (out of water) | D89: X | E89: X | F89: X | G89: X | H89: X | I89: X | J89: X | K89: X | L89: X | M89: X | N89: X | O89: X
B90: Rowboats or canoes (out of water) | C90: Preservation of Property | D90: X | E90: X | F90: X | G90: X | H90: X | I90: X | J90: X | K90: X | L90: X | M90: X | N90: X | O90: X
B91: Rowboats or canoes (out of water) | C91: Property Off-Premises | D91: X | E91: X | F91: X | G91: X | H91: X | I91: X | J91: X | K91: X | L91: X | M91: X | N91: X | O91: X
B92: Rowboats or canoes (out of water) | C92: Debris Removal | D92: X | E92: X | F92: X | G92: X | H92: X | I92: X | J92: X | K92: X | L92: X | M92: X | N92: X | O92: X
B93: Rowboats or canoes (out of water) | C93: Fire Department Service Charge | D93: X | E93: X | F93: X | G93: X | H93: X | I93: X | J93: X | K93: X | L93: X | M93: X | N93: X | O93: X
B94: Rowboats or canoes (out of water) | C94: Removal of Property To Prevent a Loss | E94: X | F94: X | G94: X | H94: X | I94: X | J94: X | K94: X | L94: X | M94: X | N94: X | O94: X
B95: Rowboats or canoes (out of water) | C95: Contract Penalty Costs | F95: X
B96: Rowboats or canoes (out of water) | C96: Security After Loss | F96: X
B97: Rowboats or canoes (out of water) | C97: Claim Data or Inventory Expense | I97: X
B98: Trailers (per cov. extensions) | D98: X | E98: X | F98: X | G98: X | H98: X | I98: X | J98: X | K98: X | L98: X | M98: X | N98: X | O98: X
B99: Trailers (per cov. extensions) | C99: Preservation of Property | D99: X | E99: X | F99: X | G99: X | H99: X | I99: X | J99: X | K99: X | L99: X | M99: X | N99: X | O99: X
B100: Trailers (per cov. extensions) | C100: Property Off-Premises | D100: X | E100: X | F100: X | G100: X | H100: X | I100: X | J100: X | K100: X | L100: X | M100: X | N100: X | O100: X
...

Sheet Question & Observation Log
A1: ID | B1: Question | C1: Response | D1: Meeting Comments | E1: Question For
A2: QU0001 | B2: ISO 2012 - The 2012 ISO Commercial Property product offers coverages that may make certain coverages from the 2007 version obsolete and add new coverages. Is the intent to move to the 2012 ISO Commercial Property Product and what's SECURAs future-state planned product offering? | D2: Additional Consideration: All proprietary coverages & WRAPs would need to be reviewed and potentially replaced with equivalent ISO coverages (eg. "Broadened Business Income" through WRAPs). Duck Creek OOTB uses coverages offered through CP00102012 which , What does the get current with ISO initiative mean in detail (eg. Will we be sunsetting certain ENs, WRAPs, etc.)? Confirm if we are moving to CP00101012 as part of the get current with ISO initiative? | E2: SECURA
A3: QU0002 | B3: BASE COVERAGES - Confirm the future state plan to use ISO Base Coverages - for example: Tobacco Sales & Warehouse, Mortgageholders E&O. | D3: Note: Anything at or below Condo Association Usage (131) | E3: SECURA
A4: QU0003 | B4: PROPRIETARY COVERAGES - See PCM to confirm use of all propriety coverages in future-state
A5: QU0004 | B5: ADDITIONAL COVERAGES - Is SECURA planning to replace the coverages offered today through the Universal WRAPs to individual coverages that can be added as needed to the base coverages? | D5: e.g. coverages offered through universal WRAPs | E5: SECURA
A6: QU0005 | B6: TRADE COVERAGES - What's the future state go to market strategy for trade-specific coverages? Do you want to go to a more standard product as opposed to a bespoke/tailored product to fit your customers needs? | D6: Considerations - Tradeoff between proprietary product offering and a more ISO aligned product. Observation - a lot of the same coverages are present across the WRAPs, if we moved to a componentized model we would need to review and ensure consistent wording. | E6: SECURA
A7: QU0006 | B7: COVERAGE FLEXIBILITY - For future state, assuming there are no system constraints, would SECURA consider the ability to include coverages as needed vs. the current WRAP programs? | D7: Note: A&H has incorporated this model | E7: SECURA
A8: QU0007 | B8: MANDATORY/OPTIONAL - In future-state, assuming we move to a more flexible coverage offering, do we want to make any additional coverages conditionally mandatory based on the customers type of business? | E8: SECURA
A9: QU0008 | B9: INTERNAL - Align on usage of Product and LOB and the potential impacts to coverage, sub-coverage, etc. | D9: Property Products: BPP, Builders Risk, BI and EE, etc. Property LOBs: Commercial Property, Specialty Property, Agri-Business | E9: Rebecca
A10: QU0009 | B10: INTERNAL - Align on definitions of Coverage Effects. | E10: Rebecca
A11: QU0010 | B11: WRAP LIMIT - Is SECURA planning to move to a single Universal WRAP with flex limits (as per discussion in Property Workshop 1)? For example, the concept that's used in the 2 Elite Wraps (250K vs 500K). | E11: SECURA
A12: QU0011 | B12: Do you view the following coverages as: - Ordinance and Law OR A. Demolition Cost B. Coverage of Undamaged Portion of the Building C. Increased Cost of Construction/Increased Period of Restoration -Broadened Business Income vs. BI&EE, Civil Authority, etc. | C12: Ordinance and Law Broadened Biz Income - Keep Granular | E12: SECURA - Claims
A13: QU0012 | B13: For coverages introduced through the Base Form but re-defined through a Wrap, how do you handle claims filed against them? Do you file against the Base Coverage or the Coverage provided, and re-defined, through the WRAP? (e.g., Personal Property of Members, Customers & Guests vs Personal Property of Others - they have individual limits) | C13: Personal Property of Members, Customers & Guests | D13: Filter: Product (Monoline Building & Personal Property), Coverage (Personal Property of Others) | E13: SECURA - Claims
A14: QU0013 | B14: For coverages introduced through a WRAP, how do you handle claims filed against them? (e.g., Theft of Telephone or Dataline Services) Is this filed as a Sub-Coverage (with a sub-limit) of Business Personal Property, or is it filed as a standalone Coverage? | D14: Filter: Product (Monoline Building & Personal Property) Scroll down | E14: SECURA - Claims
A15: QU0014 | B15: For coverages introduced through a Universal WRAP but re-defined through a Trade Wrap, how do you handle claims filed against them? (e.g. Closed Circuit TV Revenue, Patent Infringement Expense Reimbursement). Are these filed as Sub-Coverages of Broadened Business Income (introduced via the Universal Wrap), or are they filed as standalone Coverages? | D15: Filter: Coverages (Broadened Business Income) | E15: SECURA - Claims
A16: QU0015 | B16: Confirm that we are aligned on how we view coverages (see PCM: Building & Personal Property - Building Coverages)

Sheet Product Matrix - Archive
A1: Coverage | B1: Sub-Coverage | C1: Building and Personal Property | D1: Universal Wrap CPT9099 | E1: Inn Wrap CPT 2000 | F1: Human Services Property Wrap NEW - CPT 3500 | G1: Restaurant Wrap CPT 4500 | H1: Contractor and Services Wrap CPT 5500 | I1: Green Industry Contractor Wrap CPT5506 | J1: Manufacturer Wrap CPT 6000
A2: Building | D2: $125,000
B3: Debris Removal | C3: X | D3: Flex Limit (Would Remove for Coverage View)
B4: Electronic Data | C4: X | D4: Flex Limit
B5: Fine Arts At Described Premises | C5: X | D5: Flex Limit
B6: Fire Extinguisher Recharge | C6: X | D6: Flex Limit
B7: Personal Property Of Others (excluding employee tools) | C7: X | D7: Flex Limit
B8: Public Safety Service Charges | D8: Flex Limit
A9: Accounts Receivable (Other Than Electronic Data) On Premises | D9: $25,000
A10: Accounts Receivable (Other Than Electronic Data) Off Premises | D10: X (NEW - $5,000)
A11: Additional Covered Property (Foundations, walks, etc.) | D11: $50,000 (was $10,000)
A12: Additional Covered Property (BPP on structures or in portable units) | D12: NEW - Included in BPP Limit
A13: Broadened Business Income | D13: $25,000 | E13: $50,000 (was $25,000) | J13: $100,000
B14: Civil Authority | D14: Included in BBI Limit | E14: Included in BBI Limit | J14: Included in BBI Limit
B15: Lost Lease Protection | D15: Included in BBI Limit | E15: Included in BBI Limit | J15: Included in BBI Limit
B16: Dependent/Secondary Property Income | D16: Included in BBI Limit | E16: Included in BBI Limit | J16: Included in BBI Limit
B17: Extended Period of Indemnity | D17: NEW - 60 days
A18: Broadened Premises | D18: 1000 feet
A19: BPP - Seasonal Increase | D19: $100,000 or 25% Whichever is Less | I19: 30%
A20: Computer and Funds Transfer Fraud | D20: $5,000 Funds Transfer Fraud Added
A21: Employee Theft | D21: $10,000
A22: Forgery or Alteration (from Office WRAP) | D22: NEW - $25,000
A23: Landlord Furnishings | D23: NEW -Included in Bldg Limit
A24: Lock Replacement due to Theft of Your Keys or Transmitter | D24: $1,000 Deductible dropped from $500 to $0
A25: Money and Securities On | D25: $10,000
A26: Money and Securities Off | D26: $10,000
A27: Money Orders and Counterfeit Money (from Inn WRAP) | D27: NEW - $5,000 | I27: $10,000 (was $5,000)
A28: Newly Acquired Bldg, Cnts, Income (extend # of days to 180) | D28: $1,500,000
A29: Ordinance or Law Undamaged Portion | D29: Included in Bldg Limit
A30: Ord/Law - Tenant Improvements and Betterments | D30: Included in BPP Limit
A31: Ord/Law - Demolition and Inc Costs combined | D31: $100,000
A32: Ord/Law - Increased Period of Restoration | D32: NEW - Included in Broadened Business Income
A33: Outdoor Property - trees/shrubs/plants (limit $1,000 per item) | D33: $10,000 Limit per item increased from $500 | I33: $20,000
A34: Outdoor Property - Fences and Antennas | D34: $10,000
A35: Oudoor Signs - attached or not - limit per sign | D35: $10,000/sign (was $5k/sign)
A36: Personal Effects (Excluding Employee Tools) | D36: $10,000
A37: Property at Fair, Trade Show, or Exhibition | D37: $15,000
A38: Property in a Non-Owned Location | D38: $15,000 | J38: $25,000
A39: Property in Care of a Salesperson | D39: $10,000 (was $5,000)
A40: Property in Transit (Any Vehicle) | D40: $15,000 | J40: $50,000
A41: Photographic Or Scientific Instrument Lenses | D41: NEW - Included in BPP Limit
A42: Pollutant Clean Up and Removal | D42: $25,000
A43: Tenant Building - Required By Lease | D43: NEW - $10,000
A44: Tenant Glass Breakage | D44: $50,000 (was$5,000)
A45: Theft of Building Materials | D45: $50,000 (was$5,000)
A46: Unscheduled Structures | D46: NEW - Bldg Limit or $25,000 Whichever is Less
A47: Valuable Papers And Records (other than electronic data) On Premises | D47: $25,000
A48: Valuable Papers And Records (other than electronic data) Off Premises | D48: NEW - $5,000 Off Premises
A49: Coinsurance Waiver on Losses under $10,000 | D49: Included
A50: Covered Crime Reward | D50: $5,000
A51: Removal of Property to Prevent a Loss | D51: $1,000
A52: Deductible Provisions | D52: Included
A53: Broadened Business Income - Including Closed Circuit TV Revenue | E53: $50,000 (moved to separate limit, was in BBI $25k)
A54: Client Property - Theft By Employee | E54: $10,000.00 | F54: NEW - $10,000 | G54: NEW - $10,000 | H54: $10,000 | I54: $10,000
A55: Guest Accomodations Per Occurrence ($1,500 per Guest) | E55: $25,000.00
A56: Guests' Property | E56: $25,000.00
A57: Outdoor Property - Debris Removal Caused By Windstorm | E57: NEW - $2,500
A58: Watercraft Extension | E58: NEW - $25,000
A59: Automated External Defibrillators | F59: NEW - $5,000
A60: Clients' Property - Personal Effects ($5,000 per resident) | F60: NEW - $25,000 On/$25,000 Off
A61: Emergency Vacating Expense | F61: NEW - $15,000
A62: Fundraising Event Blackout | F62: NEW - $25,000
A63: Personal Effects Of Your Home Care Providers Away From Premise | F63: NEW - $1,000 Per Provider/ $5,000 Aggregate
A64: Accidental Discharge Clean-Up Expense | G64: NEW - $2,500
A65: Restaurant Broadened Business Income (Accidental Discharge, Food Contamination, Off Premises Special Event Cancellation, Water Boil Order) | G65: NEW - $10,000
A66: Credit Card Slips (forgery & theft, disappearance, destruction) | G66: NEW - $5,000
A67: Employee Tools ($1,000 per employee) | H67: $10,000 | I67: $10,000 | J67: $10,000
A68: Installation Including - Jobsite | H68: $25,000 | I68: $25,000
A69: Business Income - Off Premises Mobile Equipment | I69: Included
A70: Brand and Label Removal | J70: $25,000
A71: Broadened Business Income - Contingent Cargo | J71: $25,000
A72: Customer Property in Transit (Any Vehicle) | J72: $25,000
A73: Customer Property in CCC of Subcontactor | J73: $25,000
A74: Dies Patterns & Molds including Customers (Theft Limitation) | J74: $50,000
A75: Patent Infringement Expense Reimbursement | J75: $2,500
A76: Precious Metals | J76: $10,000

Sheet Product Overview
A1: Product | B1: Does SECURA Offer? | C1: Offered Monoline? | D1: Required Base Coverage
A2: Monoline Building and Personal Property | B2: Yes | C2: Yes | D2: N/A
A3: Monoline Builders Risk | B3: Yes | C3: Yes | D3: N/A
A4: Monoline Business Income (and Extra Expense) | B4: Yes | C4: Yes | D4: N/A
A5: Monoline Condominium Association | B5: Yes | C5: Yes | D5: N/A
A6: Extra Expense | B6: Yes | C6: Follow-Up, Maybe | D6: ? | E6: Example: BPP, BI
A7: Business Income (Without Extra Expense) | B7: Yes | C7: Follow-Up, Maybe | D7: ?
A8: Legal Liability | B8: Yes | C8: Follow-Up, Maybe | D8: ?
A9: Leasehold Interest | B9: Yes | C9: Follow-Up, Maybe | D9: ?
A10: Condo Commercial Unit-Owners | B10: Yes | C10: Follow-Up, leaning Yes | D10: ?
A11: Mortgageholders E&O | B11: Yes | C11: Follow-Up, Maybe | D11: ?
A12: Monoline Tobacco Sales Warehouses | B12: No | C12: No | D12: N/A

Sheet Forms View - MTG
A1: Form Type | B1: Form Number | C1: Product Name | D1: Category | E1: Proprietary or ISO | F1: Count of Forms | G1: PCM? | H1: Owner | I1: Comments | J1: Complete? | Z1: Category | AA1: Prop Or ISO | AB1: PCM?
A3: PR | B3: CP 0090 0788 | C3: COMMERCIAL PROPERTY CONDITIONS | D3: POLICY CONDITIONS | E3: ISO | F3: 30914 | G3: N/A | H3: Tulio | Z3: BASE COVERAGE FORM | AA3: ISO | AB3: N/A
A4: PR | B4: CP 0140 0706 | C4: EXCLUSION OF LOSS DUE TO VIRUS OR BACTERIA | D4: EXCLUSION | E4: ISO | F4: 30914 | G4: N/A | H4: Sal | Z4: OTHER COVERAGE FORM | AA4: Proprietary | AB4: ?
A5: PR | B5: CP 1032 0808 | C5: WATER EXCLUSION ENDORSEMENT | D5: EXCLUSION | E5: ISO | F5: 30913 | G5: N/A | H5: Sal | Z5: ENDORSEMENT | AB5: X
A6: PR | B6: CP 1030 0607 | C6: CAUSES OF LOSS – SPECIAL FORM | D6: EXCLUSION | E6: ISO | F6: 30882 | G6: N/A | Z6: POLICY CONDITIONS
A7: PR | B7: CP 0010 0607 | C7: BUILDING & PERSONAL PROPERTY COVERAGE | D7: BASE COVERAGE FORM | E7: ISO | F7: 30859 | G7: X | H7: Tulio | Z7: CAUSES OF LOSS
A8: PR | B8: CPE 0100 2105 | C8: COMPUTER AMENDATORY | D8: ENDORSEMENT | E8: Proprietary | F8: 30847 | G8: X | H8: Sal | Z8: EXCLUSION
A9: PR | B9: CPE 1075 2105 | C9: EXCLUSION – CYBER INCIDENTS PROPERTY | D9: EXCLUSION | E9: Proprietary | F9: 30847 | G9: ? | H9: Sal | I9: **I believe this grants back: Spoiler Coverage (Power Outage) & Computer Fraud | Z9: OTHER (Notices, Dec, etc.)
A10: PR | B10: CPT 9000 1301 | C10: UNIVERSAL WRAP SCHEDULE | D10: POLICY CONDITIONS | E10: Proprietary | F10: 27599 | G10: N/A | H10: Sal | I10: **Just lists out limits that are being amended | Z10: WRAP
A11: PR | B11: CPT 9099 1301 | C11: UNIVERSAL WRAP COVERAGE FORM | D11: OTHER COVERAGE FORM | E11: Proprietary | F11: 27599 | G11: X | H11: Sal
A12: PR | B12: HSB 5000 1301 | C12: EQUIPMENT BREAKDOWN WRAP CAUSES OF LOSS - BREAKDOWN | D12: OTHER COVERAGE FORM | E12: Proprietary | F12: 27423 | G12: X | H12: Sal
A13: PR | B13: CP 1504 0607 | C13: DISCRETIONARY PAYROLL EXPENSE | D13: POLICY CONDITIONS | E13: ISO | F13: 23128 | G13: X | H13: Sal | I13: **Schedules type of employees/max # of days
A14: PR | B14: CP 0030 0607 | C14: BUSINESS INCOME AND EXTRA EXPENSE COVERAGE | D14: BASE COVERAGE FORM | E14: ISO | F14: 23112 | G14: X | H14: Rohit
A15: PR | B15: CPE 0696 1301 | C15: Water Back-up And Sump Overflow (Not Flood-Related) | D15: OTHER COVERAGE FORM | E15: Proprietary | F15: 20241 | G15: X | H15: Sal
A16: PR | B16: CPE 1555 1301 | C16: BUSINESS INCOME – ACTUAL LOSS SUSTAINED | D16: POLICY CONDITIONS | E16: Proprietary | F16: 18447
A17: PR | B17: CP 1556 0607 | C17: BUSINESS INCOME CHANGES – BEGINNING OF THE PERIOD OF RESTORATION | D17: ENDORSEMENT | E17: ISO | F17: 14730 | G17: N/A | H17: Sal
A18: PR | B18: CPT 5500 1301 | C18: CONTRACTOR AND SERVICES WRAP | D18: OTHER COVERAGE FORM | E18: Proprietary | F18: 9311 | G18: X | H18: Sal
A19: PR | B19: CP 0113 1002 | C19: WISCONSIN CHANGES | D19: ENDORSEMENT | E19: ISO | F19: 8452 | G19: X | H19: Rohit
A20: PR | B20: CP 1550 1185 | C20: RADIO OR TELEVISION ANTENNAS – BUSINESS INCOME OR EXTRA EXPENSE | D20: ENDORSEMENT | E20: ISO | F20: 7819 | G20: N/A | H20: Rohit
A21: PR | B21: CP 1218 0607 | C21: LOSS PAYABLE PROVISIONS | D21: POLICY CONDITIONS | E21: ISO | F21: 6466 | H21: Rohit
A22: PR | B22: CP 0108 0520 | C22: MINNESOTA CHANGES | D22: POLICY CONDITIONS | E22: ISO | F22: 4657
A23: PR | B23: CP 0150 1000 | C23: MINNESOTA CHANGES – REPLACEMENT COST PERSONAL PROPERTY | D23: POLICY CONDITIONS | E23: ISO | F23: 4116
A24: PR | B24: CP 0149 0607 | C24: ILLINOIS CHANGES – ARTIFICIALLY GENERATED ELECTRICAL CURRENT EXCLUSION | D24: EXCLUSION | E24: ISO | F24: 2565 | G24: N/A
A25: PR | B25: CP 0157 0918 | C25: MINNESOTA CHANGES - COINSURANCE | D25: POLICY CONDITIONS | E25: ISO | F25: 2386 | G25: N/A
A26: PR | B26: CP 0128 0700 | C26: MISSOURI – CALCULATION OF ADDITIONAL PREMIUM | D26: ENDORSEMENT | E26: ISO | F26: 2331 | G26: N/A | H26: Tulio
A27: PR | B27: CP 1270 0996 | C27: JOINT OR DISPUTED LOSS AGREEMENT | D27: POLICY CONDITIONS | E27: ISO | F27: 2327 | G27: N/A | H27: Sal | I27: * Requires a CP + Builders' Risk policy by different insurers - describes terms of how a loss to covered property will be payed
A28: PR | B28: CPE 1036 1305 | C28: LIMITATIONS ON COVERAGE FOR ROOF SURFACING | D28: POLICY CONDITIONS | E28: Proprietary | F28: 2278 | G28: N/A | H28: Sal | I28: **This restricts coverage caused by wind/hail to the roof of the building
A29: PR | B29: CP 0166 0900 | C29: KENTUCKY CHANGES | D29: ENDORSEMENT | E29: ISO | F29: 2253 | G29: N/A | H29: Tulio
A30: PR | B30: CP 1040 0899 | C30: EARTHQUAKE AND VOLCANIC ERUPTION ENDORSEMENT | D30: ENDORSEMENT | E30: ISO | F30: 2248 | G30: X | H30: Tulio
A31: PR | B31: CP 0132 0120 | C31: ARIZONA CHANGES | D31: ENDORSEMENT | E31: ISO | F31: 2223 | G31: N/A | H31: Tulio
A32: PR | B32: CP 0146 0894 | C32: ARIZONA CHANGES | D32: ENDORSEMENT | E32: ISO | F32: 2195 | G32: ? | H32: Tulio | I32: This removes Fire Dept. Service Charge… from ALL Property Coverages
A33: PR | B33: CPE 0200 1301 | C33: GREENHOUSE VALUATION AMENDMENT | D33: POLICY CONDITIONS | E33: Proprietary | F33: 2193 | G33: N/A | H33: Sal | I33: **This restricts certain coverage and terms applicable to Greenhouses only (ex: ACV doesn't apply, Coinsurance applies, terms to be covered are added - 'temp must be > 40 degrees)
A34: PR | B34: CPT 7999 1301 | C34: ELITE UNIVERSAL WRAP COVERAGE FORM | D34: OTHER COVERAGE FORM | E34: Proprietary | F34: 1962 | H34: Sal
A35: PR | B35: CP 0120 0421 | C35: MICHIGAN CHANGES | D35: ENDORSEMENT | E35: ISO | F35: 1910 | G35: N/A | H35: Tulio
A36: PR | B36: CPT 7900 1301 | C36: MICHIGAN CHANGES | D36: ENDORSEMENT | E36: Proprietary | F36: 1830 | G36: N/A | H36: Tulio | I36: This is just a schedule for the Michigan Wrapper
A37: PR | B37: CPE 2411 1106 | C37: MISSOURI CHANGES – LOSS NOTICE REQUIREMENTS | D37: OTHER (Notices, Dec, etc.) | E37: Proprietary | F37: 1823 | G37: N/A
A38: PR | B38: CP 1221 0208 | C38: LOSS PAYABLE PROVISIONS - MINNESOTA | D38: POLICY CONDITIONS | E38: ISO | F38: 1451 | G38: N/A
A39: PR | B39: CP 0114 1115 | C39: NORTH DAKOTA CHANGES | D39: ENDORSEMENT | E39: ISO | F39: 1400 | G39: N/A | H39: Tulio | I39: Valued Policies 2. might be good to double check with Rebecca
A40: PR | B40: CPT 4500 1301 | C40: RESTAURANT WRAP | D40: WRAP | E40: Proprietary | F40: 1291 | G40: X | H40: Sal
A41: PR | B41: CP 0152 0796 | C41: INDIANA CHANGES – RIGHTS OF RECOVERY | D41: ENDORSEMENT | E41: ISO | F41: 1200 | G41: N/A | H41: Tulio
A42: PR | B42: PLI 0963 1301 | C42: INDIANA - NOTICE REGARDING MINE SUBSIDENCE COVERAGE | D42: OTHER (Notices, Dec, etc.) | E42: Proprietary | F42: 1188
A43: PR | B43: CPT 3500 2011 | C43: HUMAN SERVICES PROPERTY WRAP | D43: WRAP | E43: Proprietary | F43: 1161
A44: PR | B44: CP 0120 0918 | C44: MICHIGAN CHANGES | D44: ENDORSEMENT | E44: ISO | F44: 1020 | G44: N/A | H44: Tulio
A45: PR | B45: CP 1211 1000 | C45: BURGLARY AND ROBBERY PROTECTIVE SAFEGUARDS | D45: POLICY CONDITIONS | E45: ISO | F45: 987 | G45: N/A | H45: Tulio | I45: This is a provision, that the insured must maintain alarm systems
A46: PR | B46: CPT 7550 1301 | C46: ELITE CONTRACTOR WRAP | D46: WRAP | E46: Proprietary | F46: 942
A47: PR | B47: CP 1910 0695 | C47: YOUR BUSINESS PERSONAL PROPERTY – SEPARATION OF COVERAGE | D47: ENDORSEMENT | E47: ISO | F47: 895 | G47: N/A | H47: Tulio
A48: PR | B48: CPT 6000 1301 | C48: MANUFACTURER WRAP | D48: WRAP | E48: Proprietary | F48: 891 | I48: =97/2 -> 48.5
A49: PR | B49: CP 0320 1092 | C49: MULTIPLE DEDUCTIBLE FORM | D49: ENDORSEMENT | E49: ISO | F49: 874 | G49: ? | H49: Tulio | I49: Rebecca, what do we do in this instance?
A50: PR | B50: CP 0440 0607 | C50: SPOILAGE COVERAGE | D50: ENDORSEMENT | E50: ISO | F50: 729 | G50: X | H50: Tulio
A51: PR | B51: CP 1410 0695 | C51: ADDITIONAL COVERED PROPERTY | D51: ENDORSEMENT | E51: ISO | F51: 682 | G51: X | H51: Tulio
A52: PR | B52: CP 0321 0607 | C52: WINDSTORM OR HAIL PERCENTAGE DEDUCTIBLE | D52: ENDORSEMENT | E52: ISO | F52: 600 | G52: X | H52: Tulio
A53: PR | B53: CPT 7610 1301 | C53: ELITE MANUFACTURING WRAP | D53: WRAP | E53: Proprietary | F53: 474
A54: PR | B54: CP 0405 0402 | C54: ORDINANCE OR LAW COVERAGE | D54: ENDORSEMENT | E54: ISO | F54: 464 | G54: X | H54: Tulio
A55: PR | B55: HEE 3435 1301 | C55: BREAKDOWN COVERAGE MODIFICATION SCHEDULE – METALS and MANUFACTURING | D55: ENDORSEMENT | E55: Proprietary | F55: 441
A56: PR | B56: CPT 2000 2011 | C56: INN WRAP | D56: WRAP | E56: Proprietary | F56: 416
A57: PR | B57: CP 1219 0607 | C57: ADDITIONAL INSURED – BUILDING OWNER | D57: ENDORSEMENT | E57: ISO | F57: 389 | G57: N/A | H57: Tulio
A58: PR | B58: CP 1545 0607 | C58: UTILITY SERVICES – TIME ELEMENT | D58: ENDORSEMENT | E58: ISO | F58: 372 | G58: X | H58: Tulio
A59: PR | B59: CP 1440 0607 | C59: OUTDOOR SIGNS | D59: ENDORSEMENT | E59: ISO | F59: 352 | G59: X | H59: Tulio
A60: PR | B60: CPE 0431 1301 | C60: FOOD CONTAMINATION | D60: ENDORSEMENT | E60: Proprietary | F60: 290 | G60: ? | H60: Rohit | I60: This coverage is applicable to BI and BIEE. Should we include them under BI and BIEE
A61: PR | B61: CP 0417 0607 | C61: UTILITY SERVICES – DIRECT DAMAGE | D61: ENDORSEMENT | E61: ISO | F61: 245 | G61: X | H61: Tulio
A62: PR | B62: CP 0101 0619 | C62: KANSAS CHANGES | D62: ENDORSEMENT | E62: ISO | F62: 241 | G62: N/A | H62: Tulio
A63: PR | B63: CPE 4040 2104 | C63: TREES - EXPANDED CAUSES OF LOSS | D63: ENDORSEMENT | E63: Proprietary | F63: 231 | G63: ? | H63: Rohit | I63: Similar to CPE 0431 1301
A64: PR | B64: CPT 7450 1301 | C64: ELITE RETAIL AND WHOLESALE WRAP | D64: WRAP | E64: Proprietary | F64: 231
A65: PR | B65: CPE 4060 2104 | C65: TREES SHRUBS AND PLANTS SUPPLEMENTAL DEBRIS REMOVAL | D65: ENDORSEMENT | E65: Proprietary | F65: 220 | G65: ? | H65: Rohit | I65: COMMERCIAL PROPERTY and STANDARD PROPERTY
A66: PR | B66: CPE 0474 1301 | C66: ADDITIONAL INTEREST ENDORSEMENT | D66: ENDORSEMENT | E66: Proprietary | F66: 201
A67: PR | B67: CP 1420 0788 | C67: ADDITIONAL PROPERTY NOT COVERED | D67: EXCLUSION | E67: ISO | F67: 186 | G67: N/A | H67: Sal | I67: This looks like a schedule of property not covered? If so, I don't think this applies
A68: PR | B68: CPT 4800 2104 | C68: GOLF COURSE PROPERTY WRAP | D68: WRAP | E68: Proprietary | F68: 184
A69: PR | B69: CPT 5506 1301 | C69: GREEN INDUSTRY CONTRACTOR WRAP | D69: WRAP | E69: Proprietary | F69: 162
A70: PR | B70: CPE 9000 1102 | C70: DOMESTIC ANIMAL BAILEE COVERAGE | D70: OTHER COVERAGE FORM | E70: Proprietary | F70: 152
A71: PR | B71: CP 0438 0607 | C71: FUNCTIONAL BUILDING VALUATION | D71: ENDORSEMENT | E71: ISO | F71: 149 | G71: X | H71: Sal
A72: PR | B72: HEE 1030 1301 | C72: BREAKDOWN COVERAGE MODIFICATION SCHEDULE – PRINTING INDUSTRY | D72: ENDORSEMENT | E72: Proprietary | F72: 145 | G72: ? | H72: Rohit
A73: PR | B73: HEE 1004 1301 | C73: EQUIPMENT BREAKDOWN COVERAGE MODIFICATION SCHEDULE | D73: ENDORSEMENT | E73: Proprietary | F73: 141
A74: PR | B74: CP 1230 0695 | C74: PEAK SEASON LIMIT OF INSURANCE | D74: ENDORSEMENT | E74: ISO | F74: 134 | G74: N/A | H74: Sal | I74: Sub-limits scheduled property
A75: PR | B75: CPT 7905 1301 | C75: ELITE UNIVERSAL WRAP SCHEDULE | D75: OTHER (Notices, Dec, etc.) | E75: Proprietary | F75: 132
A76: PR | B76: CP 0017 0607 | C76: CONDOMINUM ASSOCIATION COVERAGE | D76: BASE COVERAGE FORM | E76: ISO | F76: 131 | G76: X | H76: Tulio
A77: PR | B77: CPE 6010 1908 | C77: TANK LEAKAGE AND PRODUCT CONTAMINATION | D77: ENDORSEMENT | E77: Proprietary | F77: 128 | G77: ? | H77: Rohit
A78: PR | B78: CPE 6000 1908 | C78: BEVERAGE MANUFACTURING COVERAGE ENDORSEMENT | D78: ENDORSEMENT | E78: Proprietary | F78: 125
A79: PR | B79: CP 0020 0607 | C79: BUILDERS RISK COVERAGE | D79: BASE COVERAGE FORM | E79: ISO | F79: 120 | G79: X | H79: Tulio
A80: PR | B80: CP 0050 0607 | C80: EXTRA EXPENSE COVERAGE | D80: BASE COVERAGE FORM | E80: ISO | F80: 78 | G80: X | H80: Rohit
A81: PR | B81: CPE 0018 1301 | C81: CONDOMINIUM COMMERCIAL UNIT-OWNERS COVERAGE AMENDMENT | D81: ENDORSEMENT | E81: Proprietary | F81: 71
A82: PR | B82: CPE 0100 1301 | C82: COMPUTER AMENDATORY | D82: OTHER COVERAGE FORM | E82: Proprietary | F82: 67
A83: PR | B83: CP 0197 1105 | C83: IOWA – STANDARD FIRE POLICY PROVISIONS | D83: ENDORSEMENT | E83: ISO | F83: 64 | G83: N/A | H83: Sal | I83: I believe this is just a notice - didn't find coverage
A84: PR | B84: IL1201 1185 - PR | C84: Policy Changes | D84: OTHER (Notices, Dec, etc.) | F84: 59
A85: PR | B85: CPT 7510 1301 | C85: ELITE SERVICES WRAP | D85: WRAP | E85: Proprietary | F85: 48
A86: PR | B86: CPT 7800 2104 | C86: ELITE GOLF COURSE PROPERTY WRAP | D86: WRAP | E86: Proprietary | F86: 46
A87: PR | B87: CP 1010 0607 | C87: CAUSES OF LOSS – BASIC FORM | D87: CAUSES OF LOSS | E87: ISO | F87: 45
A88: PR | B88: CP 0040 0607 | C88: LEGAL LIABILITY COVERAGE | D88: BASE COVERAGE FORM | E88: ISO | F88: 44 | G88: X | H88: Tulio
A89: PR | B89: CPE 0606 1001 | C89: HEPATITIS A COVERAGE | D89: ENDORSEMENT | E89: Proprietary | F89: 44 | I89: *Business Income - A.5.Additional Coverages: Adds Hep A Coverage
A90: PR | B90: CP 1020 0607 | C90: CAUSES OF LOSS – BROAD FORM | D90: CAUSES OF LOSS | E90: ISO | F90: 43
A91: PR | B91: CP 1113 0695 | C91: BUILDERS RISK RENOVATIONS | D91: ENDORSEMENT | E91: ISO | F91: 43 | G91: X | H91: Sal
A92: PR | B92: CP 1415 0788 | C92: ADDITIONAL BUILDING PROPERTY | D92: ENDORSEMENT | E92: ISO | F92: 42 | G92: N/A | H92: Sal | I92: **Is this old? Is this needed using the the new 1020 Builders Risk? This is just a schedule of buildings that are covered.
A93: PR | B93: CP 1310 0402 | C93: VALUE REPORTING FORM | D93: POLICY CONDITIONS | E93: ISO | F93: 41
A94: PR | B94: CP 0415 1000 | C94: DEBRIS REMOVAL ADDITIONAL INSURANCE | D94: POLICY CONDITIONS | E94: ISO | F94: 40 | I94: *Increases Limits at specified locations
A95: PR | B95: CPT 7455 1301 | C95: ELITE GROCERS VALUE WRAP | D95: WRAP | E95: Proprietary | F95: 40
A96: PR | B96: CPE 1093 1305 | C96: ROOF SURFACING – ACTUAL CASH VALUE LOSS SETTLEMENT | D96: ENDORSEMENT | E96: Proprietary | F96: 37 | I96: *Roof Surfacing ACV Coverage?
A97: PR | B97: CP 9930 0695 | C97: MANUFACTURER'S SELLING PRICE FINISHED "STOCK" ONLY | D97: ENDORSEMENT | E97: ISO | F97: 33 | G97: N/A | H97: Sal | I97: Policy Conditions
A98: PR | B98: CP 0418 0607 | C98: CONDOMINIUM COMMERCIAL UNIT-OWNERS OPTIONAL COVERAGES | D98: ENDORSEMENT | E98: ISO | F98: 32 | G98: X | H98: Tulio
A99: PR | B99: CP 1120 0607 | C99: BUILDERS RISK – COLLAPSE DURING CONSTRUCTION | D99: ENDORSEMENT | E99: ISO | F99: 32 | G99: X | H99: Sal | I99: * Adds Collapse to Builders Risk
A100: PR | B100: CP 1330 0607 | C100: AGRICULTURAL PRODUCTS STORAGE | D100: OTHER COVERAGE FORM | E100: ISO | F100: 30
A101: PR | B101: CP 0443 1005 | C101: MINNESOTA CHANGES – FUNCTIONAL BUILDING VALUATION | D101: ENDORSEMENT | E101: ISO | F101: 27 | G101: X | H101: Tulio
...

Sheet Temporary - TODO & Status
A1: Item | B1: Owner | C1: Status | F1: Draft but Row is Complete
A2: CP0010 - ISO in PCM | B2: Tulio | C2: Complete | F2: Internally Reviewed
A3: CP0020, 0030 (Core Form Amendments) - in PCM | B3: Tulio | C3: Complete | F3: Question for Rebecca
A4: Duck Creek Forms Inventory XLS | B4: Rohit | C4: Complete | F4: Need Client Input/Suggestions
A5: Duck Creek Forms Extract PDF | B5: Rohit | C5: Complete | F5: Ready for Client Discussion
A6: Endorsement Coverage Forms | B6: Sal | C6: In Progress

Sheet Ref Connect Pull
A1: LOB | B1: ISO / SECURA | C1: SECURA PSR# | D1: Form Number | F1: Title | G1: State | H1: 08 11 Changes | I1: Adoption Date | J1: Expired | K1: Rule # | L1: Blocked ISO Rule | M1: CoverAll Not Supported | N1: Static / Variable | O1: Default | P1: Override Type | Q1: ISO Schedule | R1: Supplemental Declaration | S1: Static/Variable | T1: Auto Attach VS Manual Attach | U1: PW Product Screen Entry | V1: Form Tab Manual Screen Entry | W1: Addl Interest | X1: Base Form Attachment Criteria | Y1: SECURA Customization | Z1: Testing Notes | AA1: Property Dec Print- Optional Coverages and Policy Optional Coverages sections | AB1: Coverage Form Trigger | AC1: Turn Off/ Customization | AD1: CoverAll does not support | AE1: Circular | AF1: Filing ID | AG1: ISO Footnote | AH1: Not On CoverAll List | AI1: Form Number | AJ1: Topic (from Master Test List) JE | AK1: Customize (from Master Test List) JE | AM1: Covered in Regression (Y/N) | AN1: Sample Regression Name | AO1: Transaction Name
A2: All | B2: SECURA | C2: RQ-734 | D2: ALD 0001 1204 | E2: =VLOOKUP(LOWER(TRIM(D2)),'Property Forms Usage'!#REF!,1,0) -> #REF! | F2: COMMON POLICY DECLARATIONS | I2: 41654 | S2: Variable | Y2: Defaults on the policy when renewal rewards, account credit, an association or program factor or commission change applies to the policy.
A3: All | B3: SECURA | D3: ALD 9999 0711 | E3: =VLOOKUP(LOWER(TRIM(D3)),'Property Forms Usage'!#REF!,1,0) -> #REF! | F3: OFFICER SIGNATURE PAGE | I3: 44738 | S3: Variable | Y3: Attaches to all policies.
A4: PR | B4: SECURA | C4: 71128 | D4: AGP 0184 1001 | E4: =VLOOKUP(LOWER(TRIM(D4)),'Property Forms Usage'!#REF!,1,0) -> #REF! | F4: Waiver Of Deductible - Commodities | I4: 41640 | N4: System Variable | P4: Both | Q4: Yes | R4: No | S4: Variable | T4: Manual | V4: yes | W4: N | Y4: Form should be available for manual selection when the Market Segment = Agribusiness.
A5: PR | B5: ISO | C5: 61780 | D5: CP00100607 | E5: =VLOOKUP(LOWER(TRIM(D5)),'Property Forms Usage'!#REF!,1,0) -> #REF! | F5: Building And Personal Proerty Coverage Form | I5: 41275 | K5: 14ex 30 31 32 35 36 38 68 70 71 | L5: 69 | N5: Static | Q5: No | R5: No | S5: Static | T5: Automatic | V5: n/a | X5: Loc Bldg screen/ Property Coverages section/ select Building Coverage -AND/OR- select Personal Property Coverage/ select Business Personal Property, Personal Property Of Others Coverage, or Condominium Commercial Unit-Owners Coverage | Y5: CPE 0018 along with CP0010 replace CP0018. | AB5: n/a | AE5: LI-CF-2008-059 | AF5: CF-2007-OFR07 | AJ5: ISO Exception Rule 69 - AZ KS MN MO PA
A6: PR | B6: ISO | D6: CP00170607 | E6: =VLOOKUP(LOWER(TRIM(D6)),'Property Forms Usage'!#REF!,1,0) -> #REF! | F6: Condominium Association Coverage Form | I6: 39813 | K6: 14 30 31 38 | L6: 69 | N6: Static | S6: Static | T6: Automatic | V6: n/a | X6: bldg cov screen/select "condominium association" as coverage | AB6: n/a | AE6: LI-CF-2008-059 | AF6: CF-2007-OFR07
A7: PR | B7: ISO | C7: 61780 | D7: CP00180607 | E7: =VLOOKUP(LOWER(TRIM(D7)),'Property Forms Usage'!#REF!,1,0) -> #REF! | F7: Condominium Commercial Unit-Owners Coverage Form | I7: 41275 | K7: 14ex 31 35 36 37 38 | N7: Static | S7: Static | T7: Automatic | V7: n/a | X7: Loc Bldg/ Personal Property Coverage screen - Coverage Type section/ Personal Property Coverage Options = Condominium Commercial Unit-Owners Coverage | Y7: CPE 0018 along with CP0010 replace CP0018. | Z7: SECURA Customization - SECURA will use CPE 0018 and CP 0010 in place of CP 0018. See Defaults Customization - Working as Expected | AB7: n/a | AE7: LI-CF-2008-059 | AF7: CF-2007-OFR07
A8: PR | B8: ISO | D8: CP00200607 | E8: =VLOOKUP(LOWER(TRIM(D8)),'Property Forms Usage'!#REF!,1,0) -> #REF! | F8: Builders Risk Coverage Form | I8: 39813 | K8: 38 40 41 | N8: Static | S8: Static | T8: Automatic | V8: n/a | X8: loc screen/class code = 1150 | AB8: n/a | AE8: LI-CF-2008-059 | AF8: CF-2007-OFR07
A9: PR | B9: ISO | D9: CP00300607 | E9: =VLOOKUP(LOWER(TRIM(D9)),'Property Forms Usage'!#REF!,1,0) -> #REF! | F9: Business Income (And Extra Expense) Coverage Form | I9: 39813 | K9: 50 51 54 A2 | N9: Static | Q9: No | R9: No | S9: Static | T9: Automatic | V9: n/a | X9: Loc Bldg screen/ Property Coverages Section/ select Business Income// Business Income screen/ Coverage Information section/ Coverage Form = And Extra Expense | AB9: n/a | AE9: LI-CF-2008-059 | AF9: CF-2007-OFR07
A10: PR | B10: ISO | D10: CP00320607 | E10: =VLOOKUP(LOWER(TRIM(D10)),'Property Forms Usage'!#REF!,1,0) -> #REF! | F10: Business Income (Without Extra Expense) Coverage Form | I10: 39813 | K10: 50 51 54 A1 | N10: Static | S10: Static | T10: Automatic | V10: n/a | X10: loc screen/select Business Income/On business income screen the coverage form = without Extra Expense | AB10: n/a | AE10: LI-CF-2008-059 | AF10: CF-2007-OFR07
A11: PR | B11: ISO | D11: CP00400607 | E11: =VLOOKUP(LOWER(TRIM(D11)),'Property Forms Usage'!#REF!,1,0) -> #REF! | F11: Legal Liability Coverage Form | I11: 39813 | K11: 66 72 | N11: Static | S11: Static | T11: Automatic | V11: n/a | X11: Bldg screen/Building Coverage/Coverage (Building defaults)/select Legal Liability and/or BPP screen/Personal Property Coverage Options/select Legal Liability Coverage radio button | AB11: n/a | AE11: LI-CF-2008-059 | AF11: CF-2007-OFR07
A12: PR | B12: ISO | D12: CP00500607 | E12: =VLOOKUP(LOWER(TRIM(D12)),'Property Forms Usage'!#REF!,1,0) -> #REF! | F12: Extra Expense Coverage Form | I12: 39813 | K12: 52 53 A1 | L12: 53.B.5 | N12: Static | S12: Static | T12: Automatic | V12: n/a | X12: loc screen/Extra Expense, then complete new screen | AB12: n/a | AE12: LI-CF-2008-059 | AF12: CF-2007-OFR07
A13: PR | B13: ISO | D13: CP00600695 | E13: =VLOOKUP(LOWER(TRIM(D13)),'Property Forms Usage'!#REF!,1,0) -> #REF! | F13: Leasehold Interest Coverage Form | I13: 39813 | K13: 32 65 | N13: Static | S13: Static | T13: Automatic | V13: n/a | X13: Bldg Screen - drop down for Covg Info - choose Leasehold - fill out several other boxes | AB13: n/a | AG13: (2)
A14: PR | B14: ISO | D14: CP00700607 | E14: =VLOOKUP(LOWER(TRIM(D14)),'Property Forms Usage'!#REF!,1,0) -> #REF! | F14: Mortgageholders Errors And Omissions Coverage Form | I14: 39813 | K14: 14 38 67 | N14: Static | S14: Static | T14: Automatic | V14: n/a | X14: loc screen/mortgageholders e&o, then complete new screen | AB14: n/a | AE14: LI-CF-2008-059 | AF14: CF-2007-OFR07
A15: PR | B15: ISO | D15: CP00800607 | E15: =VLOOKUP(LOWER(TRIM(D15)),'Property Forms Usage'!#REF!,1,0) -> #REF! | F15: Tobacco Sales Warehouses Coverage Form | I15: 39813 | K15: 14ex 38 | L15: 68 | N15: Static | S15: Static | T15: Automatic | V15: n/a | X15: loc screen/tobacco sales warehouses coverage, then complete new screen | Z15: blocking rule | AB15: n/a | AE15: LI-CF-2008-059 | AF15: CF-2007-OFR07
A16: PR | B16: ISO | D16: CP00900788 | E16: =VLOOKUP(LOWER(TRIM(D16)),'Property Forms Usage'!#REF!,1,0) -> #REF! | F16: Commercial Property Conditions | I16: 39813 | K16: 14 67 | L16: 69 | N16: Static | Q16: No | R16: No | S16: Static | T16: Automatic | V16: n/a | X16: Mandatory | Z16: this form is not applicable when CP0070 is on policy | AB16: n/a | AE16: CF-88-68 | AG16: (2)
A17: PR | B17: ISO | D17: CP00990607 | E17: =VLOOKUP(LOWER(TRIM(D17)),'Property Forms Usage'!#REF!,1,0) -> #REF! | F17: Standard Property Policy | G17: Not KS | I17: 39813 | K17: 14 14ex 31 38 | L17: 69 | N17: Static | S17: Static | T17: Automatic | V17: n/a | X17: comml prop screen- standard prop pol checkbox | Z17: blocking rule | AB17: n/a | AE17: LI-CF-2008-059 | AF17: CF-2007-OFR07 | AJ17: ISO Exception Rule 69 - AZ KS MN MO PA
A18: PR | B18: ISO | D18: CP01010105 | E18: =VLOOKUP(LOWER(TRIM(D18)),'Property Forms Usage'!#REF!,1,0) -> #REF! | F18: Kansas Changes | G18: KS | I18: 38353 | J18: 40909 | K18: 14ex 30ex | N18: Static | S18: Static | T18: Automatic | V18: n/a | X18: Attach when State = KS | AB18: Commercial Property Coverage Part | AE18: LI-CL-2004-068 | AF18: CL-2004-OEND1
A19: PR | B19: ISO | D19: CP01010112 | E19: =VLOOKUP(LOWER(TRIM(D19)),'Property Forms Usage'!#REF!,1,0) -> #REF! | F19: Kansas Changes | G19: KS | I19: 40909 | J19: 43952 | S19: Static
A20: PR | B20: ISO | D20: CP01010619 | E20: =VLOOKUP(LOWER(TRIM(D20)),'Property Forms Usage'!#REF!,1,0) -> #REF! | F20: Kansas Changes | G20: KS | I20: 43952 | K20: 14ex 30ex | N20: Static | S20: Static | T20: Automatic | V20: n/a | X20: Attach when State = KS | AB20: Commercial Property Coverage Part | AE20: LI-CL-2004-068 | AF20: CL-2004-OEND1
A21: PR | B21: ISO | D21: CP01060896 | E21: =VLOOKUP(LOWER(TRIM(D21)),'Property Forms Usage'!#REF!,1,0) -> #REF! | F21: Minnesota Changes - Condominiums | G21: MN | I21: 35278 | K21: 14ex | N21: Static | S21: Static | T21: Automatic | V21: n/a | X21: Attach when State = MN and Condominium class code | AB21: Condominium Association Coverage Form
A22: PR | B22: ISO | D22: CP01070695 | E22: =VLOOKUP(LOWER(TRIM(D22)),'Property Forms Usage'!#REF!,1,0) -> #REF! | F22: Condominium Additional Provisions | G22: AZ MO PA | I22: 39813 | K22: 14 14ex | N22: Static | S22: Static | T22: Automatic | V22: n/a | X22: Attach when State = AZ MO or PA. Must be condo association and on bldg screen select checkbox "created after 19xx…" | AB22: Condominium Association Coverage Form
A23: PR | B23: ISO | D23: CP01080208 | E23: =VLOOKUP(LOWER(TRIM(D23)),'Property Forms Usage'!#REF!,1,0) -> #REF! | F23: Minnesota Changes | G23: MN | I23: 39479 | J23: 43952 | K23: 14ex | N23: Static | S23: Static | T23: Automatic | V23: n/a | X23: Attach when State = MN | AB23: Commercial Property Coverage Part | AE23: LI-CF-2008-118 | AF23: CF-2007-OFR07
A24: PR | B24: ISO | C24: 48565/RQ-1338 | D24: CP01080520 | E24: =VLOOKUP(LOWER(TRIM(D24)),'Property Forms Usage'!#REF!,1,0) -> #REF! | F24: Minnesota Changes | G24: MN | I24: 43952 | K24: 14ex | N24: Static | S24: Static | T24: Automatic | V24: n/a | X24: Attach when State = MN | AB24: Commercial Property Coverage Part | AE24: LI-CF-2008-118 | AF24: CF-2007-OFR07
A25: PR | B25: ISO | D25: CP01131002 | E25: =VLOOKUP(LOWER(TRIM(D25)),'Property Forms Usage'!#REF!,1,0) -> #REF! | F25: Wisconsin Changes | G25: WI | I25: 37530 | K25: 14ex | N25: Static | S25: Static | T25: Automatic | V25: n/a | X25: Attach when State = WI | AB25: Commercial Property Coverage Part | AE25: LI-CL-2002-099 | AF25: CL-2002-OEND1
A26: PR | B26: ISO | D26: CP01141099 | E26: =VLOOKUP(LOWER(TRIM(D26)),'Property Forms Usage'!#REF!,1,0) -> #REF! | F26: North Dakota Changes | G26: ND | I26: 36434 | J26: 42309 | K26: 14ex | N26: Static | S26: Static | T26: Automatic | V26: n/a | X26: Attach when State = ND | AB26: Commercial Property Coverage Part | AE26: LI-CF-1999-166 | AF26: CL-99-OABU1
A27: PR | B27: ISO | D27: CP01141115 | E27: =VLOOKUP(LOWER(TRIM(D27)),'Property Forms Usage'!#REF!,1,0) -> #REF! | F27: North Dakota Changes | G27: ND | I27: 42675 | J27: 43132 | K27: 14ex | N27: Static | Q27: No | R27: No | S27: Static | T27: Automatic | V27: n/a | X27: Attach when State = ND | AB27: Commercial Property Coverage Part | AE27: LI-CL-2015-075
A28: PR | B28: ISO | C28: RQ-1107 33626 | D28: CP01140817 | E28: =VLOOKUP(LOWER(TRIM(D28)),'Property Forms Usage'!#REF!,1,0) -> #REF! | F28: North Dakota Changes | G28: ND | I28: 43132 | K28: 14ex | N28: Static | Q28: No | R28: No | S28: Static | T28: Automatic | V28: n/a | X28: Attach when State = ND | AB28: Commercial Property Coverage Part | AE28: LI-CL-2017-040
A29: PR | B29: ISO | D29: CP01200108 | E29: =VLOOKUP(LOWER(TRIM(D29)),'Property Forms Usage'!#REF!,1,0) -> #REF! | F29: Michigan Changes | G29: MI | I29: 39448 | J29: 43132 | K29: 14ex | N29: Static | S29: Static | T29: Automatic | V29: n/a | X29: Attach when State = MI | AB29: Commercial Property Coverage Part, Standard Property Policy | AE29: LI-CF-2007-109 | AF29: CF-2007-OCH1
A30: PR | B30: ISO | C30: RQ-1107 33626 | D30: CP01200417 | E30: =VLOOKUP(LOWER(TRIM(D30)),'Property Forms Usage'!#REF!,1,0) -> #REF! | F30: Michigan Changes | G30: MI | I30: 43132 | J30: 43586 | K30: 14ex | N30: Static | S30: Static | T30: Automatic | V30: n/a | X30: Attach when State = MI | AB30: Commercial Property Coverage Part, Standard Property Policy | AE30: LI-CL-2016-085 | AF30: CL-2016-OCAN1
A31: PR | B31: ISO | C31: 40743/ RQ-1195 | D31: CP01200918 | E31: =VLOOKUP(LOWER(TRIM(D31)),'Property Forms Usage'!#REF!,1,0) -> #REF! | F31: Michigan Changes | G31: MI | I31: 43586 | J31: 44531 | K31: 14ex | N31: Static | S31: Static | T31: Automatic | V31: n/a | X31: Attach when State = MI | AB31: Commercial Property Coverage Part, Standard Property Policy
A32: PR | B32: ISO | C32: RQ-1551 | D32: CP01200421 | E32: =VLOOKUP(LOWER(TRIM(D32)),'Property Forms Usage'!#REF!,1,0) -> #REF! | F32: Michigan Changes | G32: MI | I32: 44531 | K32: 14ex | S32: Static | T32: Automatic | X32: Attach when State= MI | AB32: Commercial Property Coverage Part, Standard Property Policy | AE32: LI-CF-2020-095 | AF32: CL-2020-OCH1
A33: PR | B33: ISO | D33: CP01210695 | E33: =VLOOKUP(LOWER(TRIM(D33)),'Property Forms Usage'!#REF!,1,0) -> #REF! | F33: Standard Fire Provisions | G33: PA | K33: 14ex | N33: Static | S33: Static | T33: Automatic | V33: n/a | X33: Attach when State = PA and policy is monoline property | AB33: Commercial Property Coverage Part, Standard Property Policy
A34: PR | B34: ISO | D34: CP01280700 | E34: =VLOOKUP(LOWER(TRIM(D34)),'Property Forms Usage'!#REF!,1,0) -> #REF! | F34: Missouri - Calculation Of Additional Premium | G34: MO | I34: 36708 | K34: 14ex | N34: Static | S34: Static | T34: Automatic | V34: n/a | X34: Attach when State = MO | AB34: Commercial Property Coverage Part, Standard Property Policy | AE34: LI-CF-2000-073 | AF34: CF-2000-OAPC1
A35: PR | B35: ISO | D35: CP01320604 | E35: =VLOOKUP(LOWER(TRIM(D35)),'Property Forms Usage'!#REF!,1,0) -> #REF! | F35: Arizona Changes | G35: AZ | I35: 38139 | J35: 43952 | K35: 14ex | N35: Static | S35: Static | T35: Automatic | V35: n/a | X35: Attach when State = AZ | AB35: Commercial Property Coverage Part | AE35: LI-CL-2003-082 | AF35: CL-2003-OCH1
A36: PR | B36: ISO | C36: 48565/RQ-1338 | D36: CP01320120 | E36: =VLOOKUP(LOWER(TRIM(D36)),'Property Forms Usage'!#REF!,1,0) -> #REF! | F36: Arizona Changes | G36: AZ | I36: 43952 | K36: 14ex | N36: Static | S36: Static | T36: Automatic | V36: n/a | X36: Attach when State = AZ | AB36: Commercial Property Coverage Part | AE36: LI-CL-2003-082 | AF36: CL-2003-OCH1
A37: PR | B37: ISO | D37: CP01400706 | E37: =VLOOKUP(LOWER(TRIM(D37)),'Property Forms Usage'!#REF!,1,0) -> #REF! | F37: Exclusion Of Loss Due To Virus Or Bacteria | I37: 39813 | K37: A10 | N37: Static | Q37: No | R37: No | S37: Static | T37: Automatic | V37: n/a | X37: Mandatory | AB37: Commercial Property Coverage Part, Standard Property Policy | AE37: LI-CF-2006-206 | AF37: CF-2006-OVBEF
A38: PR | B38: ISO | D38: CP01460894 | E38: =VLOOKUP(LOWER(TRIM(D38)),'Property Forms Usage'!#REF!,1,0) -> #REF! | F38: Arizona Changes | G38: AZ | I38: 34547 | K38: 14ex | N38: Static | S38: Static | T38: Automatic | V38: n/a | X38: Attach when State = AZ with CP0010, 0017, 0018, 0020, 0080, 0099 | AB38: Building and Personal Property Coverage Form, Condominium Association Coverage Form, Condominium Commercial Unit-Owners Coverage Form, Builders' Risk Coverage Form, Standard Property Policy, Tobacco Sales Warehouse Coverage Form | AE38: CP-94-6
A39: PR | B39: ISO | D39: CP01490607 | E39: =VLOOKUP(LOWER(TRIM(D39)),'Property Forms Usage'!#REF!,1,0) -> #REF! | F39: Illinois Changes - Artifically Generated Electrical Current Exclusion | G39: IL | I39: 39234 | K39: 14ex | N39: Static | S39: Static | T39: Automatic | V39: n/a | X39: Attach when State = IL | AB39: Commercial Property Coverage Part, Standard Property Policy | AE39: LI-CF-2008-155 | AF39: CF-2007-OFR07
A40: PR | B40: ISO | D40: CP01501000 | E40: =VLOOKUP(LOWER(TRIM(D40)),'Property Forms Usage'!#REF!,1,0) -> #REF! | F40: MINNESOTA CHANGES - REPLACEMENT COST PERSONAL PROPERTY | G40: MN | I40: 36800 | K40: 38ex | N40: Static | S40: Static | T40: Automatic | V40: n/a | X40: Attach when State = MN and Replacement Cost selected for personal property | AB40: Bulding and Personal Property Coverage Form Condominium Association Coverage Form, Condominium Commercial Unit-Owners Coverage Form | AE40: LI-CF-2002-112 | AF40: CF-99-O99FR
A41: PR | B41: ISO | D41: CP01510203 | E41: =VLOOKUP(LOWER(TRIM(D41)),'Property Forms Usage'!#REF!,1,0) -> #REF! | F41: IOWA CHANGES | G41: IA | I41: 37653 | K41: 14ex | N41: Static | S41: Static | T41: Automatic | V41: n/a | X41: Attach when State = IA with CP0040, CP0070 | AB41: Commercial Property Coverage Part, Standard Property Policy | AE41: LI-CF-2003-019 | AF41: CL-2002-OCH1
A42: PR | B42: ISO | D42: CP01520796 | E42: =VLOOKUP(LOWER(TRIM(D42)),'Property Forms Usage'!#REF!,1,0) -> #REF! | F42: INDIANA CHANGES - RIGHTS OF RECOVERY | G42: IN | I42: 35247 | K42: 14ex | N42: Static | S42: Static | T42: Automatic | V42: n/a | X42: Attach when State = IN | AB42: Commercial Property Coverage Part, Standard Property Policy
A43: PR | B43: ISO | C43: 78979 35494 RQ-1132 | D43: CP01570798 | E43: =VLOOKUP(LOWER(TRIM(D43)),'Property Forms Usage'!#REF!,1,0) -> #REF! | F43: MINNESOTA CHANGES - COINSURANCE | G43: MN | I43: 35977 | J43: 43586 | K43: 14ex | N43: System&User Variable | R43: n/a | S43: Variable | T43: Automatic | U43: Y | V43: Y | X43: Attach when State = MN Location This form should attach The ISO rules 14 ex state that this form must be attached “to all policies to which the coinsurance condition applies”. The rules further state that the endorsement “requires the signature of the insured and insurance agent”. For SECURA, -the form wouldn’t be needed for BP/TC or on any CP where the Agreed Value option is selected, -still remove these from BP/TC and CP with the ALS -the system default “signature on file” for the insured, and print the agent’s name. -but on other CP Property policies in MN, it sounds like we should be obtaining the insured’s signature on this form. -this might fit with the In-line document work Susan is doing to obtain signature from agent/insured - it is better suited to go under signature tagged documents | Y43: PSR 78979 According to ISO Rule 14ex, MN form CP0157 requires Agent and Insured signatures. Please default "Signature on file." in the Agent and Insured fields on the User Variables UI screen without user ability to modify. PSR35494 RQ-1132 - (Control Date 4/1/18.) This form should not automatically attach to any BP or CP policy. Also, it should not be available through Modify/Add Forms functionality. | AB43: Commercial Property Coverage Part | AE43: LI-CF-1999-153 | AF43: CF-98-OCH1
A44: PR | B44: ISO | C44: 40743/ RQ-1195 | D44: CP01570118 | E44: =VLOOKUP(LOWER(TRIM(D44)),'Property Forms Usage'!#REF!,1,0) -> #REF! | F44: MINNESOTA CHANGES - COINSURANCE | G44: MN | I44: 43586 | K44: 14ex | N44: System&User Variable | R44: n/a | S44: Variable | T44: Automatic | U44: Y | V44: Y | X44: Attach when State = MN Location This form should attach The ISO rules 14 ex state that this form must be attached “to all policies to which the coinsurance condition applies”. The rules further state that the endorsement “requires the signature of the insured and insurance agent”. For SECURA, -the form wouldn’t be needed for BP/TC or on any CP where the Agreed Value option is selected, -still remove these from BP/TC and CP with the ALS -the system default “signature on file” for the insured, and print the agent’s name. -but on other CP Property policies in MN, it sounds like we should be obtaining the insured’s signature on this form. -this might fit with the In-line document work Susan is doing to obtain signature from agent/insured - it is better suited to go under signature tagged documents | Y44: PSR 78979 According to ISO Rule 14ex, MN form CP0157 requires Agent and Insured signatures. Please default "Signature on file." in the Agent and Insured fields on the User Variables UI screen without user ability to modify. PSR35494 RQ-1132 - (Control Date 4/1/18.) This form should not automatically attach to any BP or CP policy. Also, it should not be available through Modify/Add Forms functionality. | AB44: Commercial Property Coverage Part
A45: PR | B45: ISO | D45: CP01660900 | E45: =VLOOKUP(LOWER(TRIM(D45)),'Property Forms Usage'!#REF!,1,0) -> #REF! | F45: KENTUCKY CHANGES | G45: KY | I45: 36770 | K45: 14ex | N45: Static | S45: Static | T45: Automatic | V45: n/a | X45: Attach when State = KY | AB45: Commercial Property Coverage Part, Standard Property Policy | AE45: LI-CF-2000-114 | AF45: CF-2000-OABU1
A46: PR | B46: ISO | D46: CP01941002 | E46: =VLOOKUP(LOWER(TRIM(D46)),'Property Forms Usage'!#REF!,1,0) -> #REF! | F46: WISCONSIN CHANGES | G46: WI | I46: 37530 | K46: 14ex | N46: Static | S46: Static | T46: Automatic | V46: n/a | X46: state on policy and with Standard Property Policies | Z46: blocking rule | AB46: Standard Property Policy | AE46: LI-CL-2002-099 | AF46: CL-2002-OEND1
A47: PR | B47: ISO | D47: CP01950896 | E47: =VLOOKUP(LOWER(TRIM(D47)),'Property Forms Usage'!#REF!,1,0) -> #REF! | F47: MINNESOTA CONDOMINIUM ASSOCIATION COVERAGE (CONDOMINIUM LAW PROVISIONS) | G47: MN | I47: 35278 | J47: Blocked | L47: 69ex | N47: Static | S47: Static | T47: Automatic | V47: n/a | X47: Blocking standard property policies | Y47: Option Blocked for SECURA | AB47: Standard Property Policy
A48: PR | B48: ISO | D48: CP01971105 | E48: =VLOOKUP(LOWER(TRIM(D48)),'Property Forms Usage'!#REF!,1,0) -> #REF! | F48: IOWA - STANDARD FIRE POLICY PROVISIONS | G48: IA | I48: 38657 | K48: 14ex | N48: Static | S48: Static | T48: Automatic | V48: n/a | X48: Attach when State = IA and policy is monoline property | AB48: Commercial Property Coverage Part, Standard Property Policy | AE48: LI-CF-2005-159 | AF48: CL-2005-OSFP1
A49: PR | B49: ISO | D49: CP01990695 | E49: =VLOOKUP(LOWER(TRIM(D49)),'Property Forms Usage'!#REF!,1,0) -> #REF! | F49: CONDOMINIUM ASSOCIATION COVERAGE CONDOMINIUM LAW PROVISIONS | G49: AZ MO PA | I49: 39813 | J49: Blocked | L49: 69 69ex | N49: Static | S49: Static | T49: Automatic | V49: n/a | X49: Blocking standard property policies | Y49: Option Blocked for SECURA | AB49: Standard Property Policy
A50: PR | B50: ISO | D50: CP03201092 | E50: =VLOOKUP(LOWER(TRIM(D50)),'Property Forms Usage'!#REF!,1,0) -> #REF! | F50: MULTIPLE DEDUCTIBLE FORM (FIXED DOLLAR DEDUCTIBLES) | I50: 39813 | K50: 81 | L50: 33 | N50: variable | Q50: Yes | R50: Yes | S50: Variable | T50: Automatic | U50: Y | V50: N | W50: N | X50: location screen/wind hail deductible is different than deductible, if bldgs or locations have different deductibles listed | AB50: Building and Personal Property Coverage Form, Builders' Risk Coverage Form, Condominium Association Coverage Form, Condominium Commercial Unit-Owners Coverage Form, Standard Property Policy, Tobacco Sales Warehouses Coverage Form | AE50: CP-94-18
A51: PR | B51: ISO | D51: CP03210607 | E51: =VLOOKUP(LOWER(TRIM(D51)),'Property Forms Usage'!#REF!,1,0) -> #REF! | F51: WINDSTORM OR HAIL PERCENTAGE DEDUCTIBLE | I51: 39813 | K51: 82 | N51: variable | Q51: Yes | R51: Yes | S51: Variable | T51: Automatic | U51: Y | V51: N | W51: N | X51: location screen/building tab/wind hail deductible is different than deductible, if bldgs or locations have different deductibles listed/choose wind & hail deductible/choose building coverage down below | AB51: Building and Personal Property Coverage Form, Builders' Risk Coverage Form, Condominium Association Coverage Form, Condominium Commercial Unit-Owners Coverage Form, Standard Property Policy, Tobacco Sales Warehouses Coverage Form | AE51: LI-CF-2008-059 | AF51: CF-2007-OFR07
A52: PR | B52: ISO | D52: CP04011000 | E52: =VLOOKUP(LOWER(TRIM(D52)),'Property Forms Usage'!#REF!,1,0) -> #REF! | F52: Brands And Labels | I52: 39813 | K52: 38 | N52: Static | S52: Static | T52: Manual | V52: n/a | X52: Location; Bldg; BPP; Optional Coverages: Brands and Labels checkbox - nothing else to fill out | AA52: Personal Property | AB52: Building and Personal Property Coverage Form, Condominium Association Coverage Form, Condominium Commercial Unit-Owners Coverage Form, Standard Property Policy | AE52: LI-CF-2000-247 | AF52: CF-99-O99FR
A53: PR | B53: ISO | D53: CP04020909 | E53: =VLOOKUP(LOWER(TRIM(D53)),'Property Forms Usage'!#REF!,1,0) -> #REF! | F53: INCREASED COST OF LOSS AND RELATED EXPENSEES FOR GREEN UPGRADES | K53: A5 | N53: variable | Q53: Yes | R53: Yes | S53: Variable | T53: Automatic | U53: Y | V53: N | W53: N | X53: Building /Optional Coverages /Green Upgrades = true | Z53: 4/22/15 JE: Working as expected | AA53: Building and under Personal Property | AB53: Building and Personal Property Coverage Form, Business Income (and Extra Expense) Coverage Form, Business Income (Without Extra Expense) Coverage Form, Condominium Association Coverage Form, Condominium Commercial Unit-Owners Coverage Form, Extra Expense Coverage Form | AE53: LI-CF-2009-233 | AF53: CF-2009-OGB09
A54: PR | B54: ISO | D54: CP04050402 | E54: =VLOOKUP(LOWER(TRIM(D54)),'Property Forms Usage'!#REF!,1,0) -> #REF! | F54: ORDINANCE OR LAW COVERAGE | I54: 39813 | K54: 38 | N54: variable | Q54: Yes | R54: Yes | S54: Variable | T54: Automatic | U54: Y | V54: N | W54: N | X54: Bldg Cov Screen/Under Optional cov/Bldg Ord then select type. Will open new screen for options | Z54: supplement goes in bldg order (all bldgs 1 reg of loc) vesus all loc 1 bldgs then loc 2 | AA54: Building | AB54: Building and Personal Property Coverage Form, Condominium Association Coverage Form, Standard Property Policy | AE54: LI-CF-2002-107 | AF54: CF-2001-O01FR
A55: PR | B55: ISO | D55: CP04071091 | E55: =VLOOKUP(LOWER(TRIM(D55)),'Property Forms Usage'!#REF!,1,0) -> #REF! | F55: POLLUTANT CLEAN UP AND REMOVAL ADDITIONAL AGGREGATE LIMIT OF INSURANCE | I55: 39813 | K55: 38 | N55: variable | Q55: Yes | R55: Yes | S55: Variable | T55: Automatic | U55: Y | V55: N | W55: N | X55: Bldg Cov Screen/Under Optional cov/Pollutant Cleanup and Removal. Will open new screen for options | Z55: 4/22/15 JE - Paul W is looking into to see if Location only cov. 4/23/15 JE - Paul W confirmed this should be 'location' only, not per building. Email to Jess M to submit SR due to screen modifications needed. ~ ~ ~ think supp should add bldg to form- does not list building number - only premise number- example: Prem 1 Prem 1 instead of Prem 1 Building 1- Prem 1 Building 2 | AA55: Building | AB55: Building and Personal Property Coverage Form, Condominium Association Coverage Form, Condominium Commercial Unit-Owners Coverage Form, Builders' Risk Coverage Form, Standard Property Policy, Tobacco Sales Warehouse Coverage Form | AE55: CP-91-43 | AG55: (2)
A56: PR | B56: ISO | C56: RQ-1069 | D56: CP04100607 | E56: =VLOOKUP(LOWER(TRIM(D56)),'Property Forms Usage'!#REF!,1,0) -> #REF! | F56: Electrical Apparatus | G56: Not IL | I56: 39234 | K56: 22 | N56: Static | Q56: Yes | R56: Yes | S56: Static | T56: Not Used | V56: n/a | X56: Manually attach | Y56: This is not a valid form for SECURA. There is a back end edit instructing the user to remove the invalid form. | Z56: IL - Use CP0410 0695 in place of CP0410 0607 | AB56: Causes of Loss-Basic Form, Causes of Loss-Borad Form, Causes of Loss-Special Form, Standard Property Policy | AE56: LI-CF-2008-059 | AF56: CF-2007-OFR07
A57: PR | B57: ISO | C57: RQ-1069 | D57: CP04100695 | E57: =VLOOKUP(LOWER(TRIM(D57)),'Property Forms Usage'!#REF!,1,0) -> #REF! | F57: Electrical Apparatus | G57: IL | K57: 22 | N57: Static | Q57: Yes | R57: Yes | S57: Variable | T57: Not Used | V57: n/a | X57: Manually attach | Y57: This is not a valid form for SECURA. There is a back end edit instructing the user to remove the invalid form. | Z57: IL - Use CP0410 0695 in place of CP0410 0607 | AB57: Causes of Loss-Basic Form, Causes of Loss-Borad Form, Causes of Loss-Special Form, Standard Property Policy | AG57: (2)
A58: PR | B58: ISO | D58: CP04151000 | E58: =VLOOKUP(LOWER(TRIM(D58)),'Property Forms Usage'!#REF!,1,0) -> #REF! | F58: DEBRIS REMOVAL ADDITIONAL INSURANCE | I58: 39813 | K58: 38 | N58: variable | Q58: Yes | R58: Yes | S58: Variable | T58: Automatic | U58: Y | V58: N | W58: N | AA58: Building | AB58: Bulders' Risk Coverage Form, Building and Personal Property Coverage Form, Condominium Association Coverage Form, Condominium Commercial Unit-Owners Coverage Form, Standard property Policy, Tobacco Sales Warehouses Coverage Form | AE58: LI-CF-2000-247 | AF58: CF-99-O99FR | AJ58: Rule 38.E.5, Rule 38.F.2 & Rule 38.F.3
A59: PR | B59: ISO | D59: CP04170607 | E59: =VLOOKUP(LOWER(TRIM(D59)),'Property Forms Usage'!#REF!,1,0) -> #REF! | F59: UTILITY SERVICES - DIRECT DAMAGE | I59: 39234 | K59: 38 | N59: variable | Q59: Yes | R59: Yes | S59: Variable | T59: Automatic | U59: Y | V59: N | W59: N | X59: Commercial Property/ Buildings/ Loc Bldg screen/ Property Coverages section/ Utility Service Coverage, then select either Bldg or BPP direct damage option on new screen | Z59: shows bpp option then bldg | AA59: Builiding and under Personal Property | AB59: Building and Personal Property Coverage Form, Builders' Risk Coverage Form, Condominium Association Coverage Form, Condominium Commercial Unit-Owners Coverage Form, Standard Property Policy, Tobacco Sales Warehouses Coverage Form | AE59: LI-CF-2008-059 | AF59: CF-2007-OFR07
A60: PR | B60: ISO | D60: CP04180607 | E60: =VLOOKUP(LOWER(TRIM(D60)),'Property Forms Usage'!#REF!,1,0) -> #REF! | F60: CONDOMINIUM COMMERCIAL UNIT-OWNERS OPTIONAL COVERAGES | I60: 39234 | K60: 38 | N60: variable | Q60: Yes | R60: Yes | S60: Variable | T60: Automatic | U60: Y | V60: N | W60: N | AA60: Personal Property | AB60: Condominium Commercial Unit-Owners-Standard Property Policy, Condominium Commercial Unit-Owners Coverage Form | AE60: LI-CF-2008-059 | AF60: CF-2007-OFR07
A61: PR | B61: ISO | D61: CP04251090 | E61: =VLOOKUP(LOWER(TRIM(D61)),'Property Forms Usage'!#REF!,1,0) -> #REF! | F61: NEWLY ACQUIRED OR CONSTRUCTED PROPERTY - INCREASED LIMIT | K61: 38 66 | N61: System Variable | Q61: Yes | R61: Yes | S61: Variable | T61: Automatic | U61: Y | V61: N | W61: N | X61: bldg cov screen/newly acquired or constructed property, then fill out the optional provision screen (**must have "None" selected in Property Wrap field on Commercial Property screen - SR 10372) | Z61: 4/17/15 HH: Working as expected | AA61: Building | AB61: Building and Personal Property Coverage Form, Condominium Association Coverage Form, Standard Property Policy, Legal Liability Coverage Form | AE61: CP-90-27
A62: PR | B62: ISO | D62: CP04300607 | E62: =VLOOKUP(LOWER(TRIM(D62)),'Property Forms Usage'!#REF!,1,0) -> #REF! | F62: ELECTRONIC COMMERCE (E-COMMERCE) | G62: Not IL | K62: 77 | N62: variable | Q62: Yes | R62: No | S62: Variable | T62: Automatic | U62: Y | V62: N | W62: N | X62: Commercial Property screen/check box for "Electronic Commerce Endorsement" under Coverage Options/fill out e-commerce screen In IL, use CP0434 in place of CP0430 | Z62: 4/22/15 HH: Working as expected | AA62: Building | AB62: Commercial Property Coverage Part | AE62: LI-CF-2008-059 | AF62: CF-2007-OFR07
A63: PR | B63: ISO | D63: CP04310402 | E63: =VLOOKUP(LOWER(TRIM(D63)),'Property Forms Usage'!#REF!,1,0) -> #REF! | F63: Changes - Fungus, Wet Rot, Dry Rot And Bacteria | I63: 39813 | K63: A6 | N63: variable | Q63: Yes | R63: No | S63: Variable | T63: Automatic | U63: Yes | V63: n/a | X63: comm prop; covg options check box; new screen w/required Revised Limit and option for separate premises or locations | Y63: Commercial Property/ Coverage Options screen/ select Fungus, Wet Rot, Dry Rot and Bacteria Increase Option Next- Commercial Property/ Fungus, Wet Rod, Dry Rot and Bacteria Coverage tab/ enter Revised Limit Next- Optional: Building/ Loc Bldg screen/ Property Coverages section/ select Business Income/ Business Income screen/ Coverage Information section/ Coverage Form = And Extra Expense/ and Coverage Options section/ enter Fungus - Increased Number of Days (If this option is not selected, Increased Number of Days will be blank on the form.) Note: The 'Separate Premises Or Locations Option' has been defaulted as "No" and hidden. "No" will always appear checked on the form. | AB63: Causes of Loss-Basic Form, Causes of Loss-Borad Form, Causes of Loss-Special Form | AE63: LI-CF-2002-107 | AF63: CF-2001-O01FR
A64: PR | B64: ISO | D64: CP04320402 | E64: =VLOOKUP(LOWER(TRIM(D64)),'Property Forms Usage'!#REF!,1,0) -> #REF! | F64: BUSINESS PERSONAL PROPERTY LIMITED INTERNATIONAL COVERAGE | J64: Blocked | L64: 38.W | N64: variable | Q64: Yes | R64: Yes | S64: Variable | T64: Automatic | V64: n/a | X64: bpp cov screen/checkbox ltd international cov -bpp, then fill out new screen | Y64: Option Blocked for SECURA | AA64: Personal Property | AB64: Building and Personal Property Coverage Form | AE64: LI-CF-2002-107 | AF64: CF-2001-O01FR
A65: PR | B65: ISO | D65: CP04330402 | E65: =VLOOKUP(LOWER(TRIM(D65)),'Property Forms Usage'!#REF!,1,0) -> #REF! | F65: PROPERTY IN PROCESS OF MANUFACTURE BY OTHERS LIMITED INTERNATIONAL COVERAGE | J65: Blocked | L65: 38.W | N65: variable | Q65: Yes | R65: Yes | S65: Variable | T65: Automatic | V65: n/a | X65: bpp cov screen/checkbox ltd international cov -property in process of mfg by others, then fill out new screen | Y65: Option Blocked for SECURA | AA65: Personal Property | AB65: Building and Personal Property Coverage Form | AE65: LI-CF-2002-107 | AF65: CF-2001-O01FR
A66: PR | B66: ISO | D66: CP04340607 | E66: =VLOOKUP(LOWER(TRIM(D66)),'Property Forms Usage'!#REF!,1,0) -> #REF! | F66: ELECTRONIC COMMERCE (E-COMMERCE) - ILLINOIS | G66: IL | K66: 77 | N66: variable | Q66: Yes | R66: No | S66: Variable | T66: Automatic | U66: Y | V66: N | W66: N | X66: Commercial Property screen/check box for "Electronic Commerce Endorsement" under Coverage Options/fill out e-commerce screen | Z66: In IL, Use CP 0434 in place of CP0430. 4/22/15 HH: Revision number gets bumped to second line at top of form, creating spacing issues. SR 10447 submitted. | AA66: Building | AB66: Commercial Property Coverage Part | AE66: LI-CF-2008-155 | AF66: CF-2007-OFR07
A67: PR | B67: ISO | D67: CP04380607 | E67: =VLOOKUP(LOWER(TRIM(D67)),'Property Forms Usage'!#REF!,1,0) -> #REF! | F67: FUNCTIONAL BUILDING VALUATION | G67: Not MN | I67: 39234 | K67: 38 | N67: variable | Q67: Yes | R67: Yes | S67: Variable | T67: Automatic | U67: Y | V67: N | W67: N | X67: bldg cov screen/functional valuation (this checkbox not available with coins below 80 and if blanketed In MN, use CP0443 in place of CP0438 | AA67: Builiding | AB67: Building and Personal Property Coverage Form, Condominium Association Coverage Form | AE67: LI-CF-2008-059 | AF67: CF-2007-OFR07 | AJ67: Rule 38.R
A68: PR | B68: ISO | D68: CP04391090 | E68: =VLOOKUP(LOWER(TRIM(D68)),'Property Forms Usage'!#REF!,1,0) -> #REF! | F68: FUNCTIONAL PERSONAL PROPERTY VALUATION (OTHER THAN STOCK) | I68: 39813 | K68: 38 | N68: variable | Q68: Yes | R68: Yes | S68: Variable | T68: Automatic | U68: Y | V68: N | W68: N | X68: Building Tab/Location 1 Building 1 Tab- choose personal property coverage at the bottom/Personal Property Coverage Tab/Check functional valuation box (this checkbox not available with coins below 80 and if blanketed | AA68: Personal Property | AB68: Building and Personal Property Coverage Form, Condominium Association Coverage Form, Condominium Commercial Unit-Owners Coverage Form | AE68: CP-90-27 | AG68: (2) | AJ68: Rule 38.S
A69: PR | B69: ISO | D69: CP04400607 | E69: =VLOOKUP(LOWER(TRIM(D69)),'Property Forms Usage'!#REF!,1,0) -> #REF! | F69: SPOILAGE COVERAGE | I69: 39813 | K69: 38 | N69: variable | Q69: Yes | R69: Yes | S69: Variable | T69: Automatic | U69: Y | V69: N | W69: N | X69: Location 1 Building 1- choose personal property coverage/pp cov screen/spoilage checkbox, then fill out new screen | AA69: Personal Property | AB69: Building and Personal Property Coverage Form, Condominium Commercial Unit-Owners Coverage Form | AE69: LI-CF-2008-059 | AF69: CF-2007-OFR07 | AJ69: Rule 38.T
A70: PR | B70: ISO | D70: CP04431005 | E70: =VLOOKUP(LOWER(TRIM(D70)),'Property Forms Usage'!#REF!,1,0) -> #REF! | F70: MINNESOTA CHANGES - FUNCTIONAL BUILDING VALUATION | G70: MN | I70: 38626 | K70: 38ex | N70: variable | Q70: Yes | R70: Yes | S70: Variable | T70: Automatic | U70: Y | V70: N | W70: N | X70: bldg cov screen/functional valuation (this checkbox not available with coins below 80 and if blanketed | Z70: In MN, use CP0443 in place of CP0438. 2 issues with CP 0443: 1-Supplement not attaching. 2- two $$ are printing on ISO form CP 0443. SR 10450 submitted. | AB70: Building and Personal Property Coverage Form, Condominium Association Coverage Form | AE70: LI-CF-2005-099 | AF70: CF-2005-O01FR
A71: PR | B71: ISO | D71: CP04500788 | E71: =VLOOKUP(LOWER(TRIM(D71)),'Property Forms Usage'!#REF!,1,0) -> #REF! | F71: VACANCY PERMIT | I71: 39813 | K71: 38 | N71: variable | Q71: Yes | R71: Yes | S71: Variable | T71: Automatic | U71: Y | V71: N | W71: N | X71: Not available when Vacancy Changes applies. Building /Optional Coverages /Vacancy Permit = true then fill out new screen | Z71: Form # printed on policy dec as expected. | AA71: Building | AB71: Building and Personal Property Coverage Form, Condominium Association Coverage Form, Condominium Commercial Unit-Owners Coverage Form, Standard Property Policy | AE71: CF-88-68 | AG71: (2)
A72: PR | B72: ISO | D72: CP04601000 | E72: =VLOOKUP(LOWER(TRIM(D72)),'Property Forms Usage'!#REF!,1,0) -> #REF! | F72: VACANCY CHANGES | I72: 39813 | K72: 38 | N72: variable | Q72: Yes | R72: Yes | S72: Variable | T72: Automatic | U72: Y | V72: N | W72: N | X72: Not available when Vacancy Permit selected. Building /Optional Coverages /Vacancy Changes = true Enter percentage. | Z72: Form not showing on policy dec as expected. This is a known issue & CoverAll stated that this would be an enhancement, therefore SR was closed due to the infrequency of the coverage. Per Jess Maxwell | AA72: Building | AB72: Building and Personal Property Coverage Form, Condominium Association Coverage Form, Condominium Commercial Unit-Owners Coverage Form, Mortgageholders Errors and Omissions Coverage Form, Standard Property Policy | AE72: LI-CF-2000-256 | AF72: CF-99-O99FR
A73: PR | B73: ISO | D73: CP09010108 | E73: =VLOOKUP(LOWER(TRIM(D73)),'Property Forms Usage'!#REF!,1,0) -> #REF! | F73: ARIZONA - AMENDMENT OF TERRORISM EXCLUSION OR SUB-LIMIT (COMMERCIAL RESIDENTIAL PROPERTY) | G73: AZ | J73: X | K73: TER | N73: Static | S73: Static | T73: Automatic | V73: n/a | X73: state on policy and federal TRIA | AB73: Commercial Property Coverage Part, Standard Property Policy | AE73: LI-CF-2008-045 | AF73: CF-2008-OTRP1
A74: PR | B74: ISO | C74: 10477/78601 | D74: CP09010115 | E74: =VLOOKUP(LOWER(TRIM(D74)),'Property Forms Usage'!#REF!,1,0) -> #REF! | F74: ARIZONA - AMENDMENT OF TERRORISM EXCLUSION OR SUB-LIMIT (COMMERCIAL RESIDENTIAL PROPERTY) | G74: AZ | I74: 42005 | K74: TER | N74: Static | Q74: No | R74: No | S74: Static | T74: Automatic | V74: n/a | X74: state on policy and federal TRIA | Y74: Rejected - Commercial Package screen/ Terrorism Certified Acts Coverage = No -AND- Class Code = 0196, 0197, 0198 | AB74: Commercial Property Coverage Part, Standard Property Policy | AE74: LI-CF-2008-045 | AF74: CF-2008-OTRP1
A75: PR | B75: ISO | D75: CP10100607 | E75: =VLOOKUP(LOWER(TRIM(D75)),'Property Forms Usage'!#REF!,1,0) -> #REF! | F75: CAUSES OF LOSS - BASIC FORM | I75: 39813 | K75: 70 71 74 84 | L75: 69 | N75: Static | S75: Static | T75: Automatic | V75: n/a | X75: bldg/bpp/bi/ee/sp cl cov screen-select cause of loss basic | AB75: n/a | AE75: LI-CF-2008-059 | AF75: CF-2007-OFR07
A76: PR | B76: ISO | D76: CP10200607 | E76: =VLOOKUP(LOWER(TRIM(D76)),'Property Forms Usage'!#REF!,1,0) -> #REF! | F76: CAUSES OF LOSS - BROAD FORM | I76: 39813 | K76: 41 71 84 | N76: Static | S76: Static | T76: Automatic | V76: n/a | X76: bldg/bpp/bi/ee/sp cl cov screen-select cause of loss broad | AB76: n/a | AE76: LI-CF-2008-059 | AF76: CF-2007-OFR07
A77: PR | B77: ISO | D77: CP10300607 | E77: =VLOOKUP(LOWER(TRIM(D77)),'Property Forms Usage'!#REF!,1,0) -> #REF! | F77: CAUSES OF LOSS - SPECIAL FORM | I77: 39813 | K77: 38 72 74 77 84 | N77: Static | S77: Static | T77: Automatic | V77: n/a | X77: bldg/bpp/bi/ee/sp cl cov screen-select cause of loss special | AB77: n/a | AE77: LI-CF-2008-059 | AF77: CF-2007-OFR07
A78: PR | B78: ISO | D78: CP10320808 | E78: =VLOOKUP(LOWER(TRIM(D78)),'Property Forms Usage'!#REF!,1,0) -> #REF! | F78: WATER EXCLUSION ENDORSEMENT | I78: 39813 | K78: A10 | N78: Static | S78: Static | T78: Automatic | V78: n/a | X78: Mandatory | AB78: Commercial Property Coverage Part, Standard Property Policy | AE78: LI-CF-2008-268 | AF78: CL-2008-OWEFO
A79: PR | B79: ISO | D79: CP10330695 | E79: =VLOOKUP(LOWER(TRIM(D79)),'Property Forms Usage'!#REF!,1,0) -> #REF! | F79: THEFT EXCLUSION | I79: 39813 | K79: 72 74 | N79: Static | S79: Static | T79: Automatic | V79: n/a | X79: Commercial Property/ Buldings/ Loc Bldg screen/ Additional Exclusions section/ Exclude Theft = Yes Note: Theft Exclusion can be removed on the Bldg/BPP/BI screen | AB79: Causes of Loss-Special Form
A80: PR | B80: ISO | D80: CP10350695 | E80: =VLOOKUP(LOWER(TRIM(D80)),'Property Forms Usage'!#REF!,1,0) -> #REF! | F80: WATERCRAFT EXCLUSION | I80: 39813 | K80: 72 | N80: Static | S80: Static | T80: Automatic | V80: n/a | X80: check box on bldg/bpp/bi screen-select option in drop down box | AB80: Causes of Loss-Special Form
A81: PR | B81: ISO | D81: CP10371000 | E81: =VLOOKUP(LOWER(TRIM(D81)),'Property Forms Usage'!#REF!,1,0) -> #REF! | F81: RADIOACTIVE CONTAMINATION | J81: Blocked | K81: 74 | L81: 74.E | N81: variable | Q81: Yes | R81: Yes | S81: Variable | T81: Automatic | U81: Y | V81: N | W81: N | X81: Select on bldg/bpp/bi screen | Y81: Option Blocked for SECURA | AB81: Causes of Loss-Basic Form, Causes of Loss-Broad Form, Causes of Loss-Special Form | AE81: LI-CF-2000-247 | AF81: CF-99-O99FR
A82: PR | B82: ISO | D82: CP10400899 | E82: =VLOOKUP(LOWER(TRIM(D82)),'Property Forms Usage'!#REF!,1,0) -> #REF! | F82: EARTHQUAKE AND VOLCANIC ERUPTION ENDORSEMENT | I82: 39783 | K82: 73 74 | N82: Static | S82: Static | T82: Automatic | V82: n/a | X82: Commercial Property/ Buldings/ Loc Bldg screen/ Building Options section/ Earthquake Coverage = Yes Note: Earthquake Coverage can be removed on the Bldg/BPP/BI screen | AB82: Commercial Property Coverage Part, Standard Property Policy | AE82: LI-CF-1999-073 | AF82: CF-99-O99EF | AG82: (2)
A83: PR | B83: ISO | C83: DF-1455 112984 | D83: CP10410899 | E83: =VLOOKUP(LOWER(TRIM(D83)),'Property Forms Usage'!#REF!,1,0) -> #REF! | F83: EARTHQUAKE INCEPTION EXTENSION | I83: 39783 | K83: 73 | N83: Static | S83: Static | T83: Automatic | V83: n/a | X83: Select on bldg/bpp/bi screen-fill out drop downs DF-1455 This form should not be used. | AB83: Earthquake and Volcanic Eruption Endorsement, Earthquake and Volcanic Eruption Endorsement (Sub-Limit Form) | AE83: LI-CF-1999-090 | AF83: CF-99-O99EF | AG83: (2)
A84: PR | B84: ISO | D84: CP10450899 | E84: =VLOOKUP(LOWER(TRIM(D84)),'Property Forms Usage'!#REF!,1,0) -> #REF! | F84: EARTHQUAKE AND VOLCANIC ERUPTION ENDORSEMENT (SUB-LIMIT FORM) | I84: 39783 | K84: 74 75 | N84: Static | S84: Static | T84: Automatic | V84: n/a | X84: Select on bldg/bpp screen | AB84: Commercial Property Coverage Part, Standard Property Policy | AE84: LI-CF-1999-073 | AF84: CF-99-O99EF | AG84: (2)
A85: PR | B85: ISO | D85: CP10510788 | E85: =VLOOKUP(LOWER(TRIM(D85)),'Property Forms Usage'!#REF!,1,0) -> #REF! | F85: Grain Properties - Explosion Limitation | I85: 39783 | K85: 70 | N85: Static | S85: Static | T85: Manual | V85: n/a | X85: manually attach, must have either broad or basic cause of loss | AB85: Causes of Loss-Basic Form, Causes of Loss-Broad Form, Standard Property Policy | AE85: CF-88-68 | AG85: (2)
A86: PR | B86: ISO | D86: CP10520607 | E86: =VLOOKUP(LOWER(TRIM(D86)),'Property Forms Usage'!#REF!,1,0) -> #REF! | F86: BROKEN OR CRACKED GLASS EXCLUSION FORM | I86: 39783 | K86: 38 | N86: variable | Q86: Yes | R86: Yes | S86: Variable | T86: Automatic | U86: Y | V86: Y | W86: N | X86: Select Broken Or Cracked Glass Exclusion checkbox under Optional Coverages on bldg/bpp screen | Z86: User entered text on Variable form needs to be more descriptive. Displayed on policy dec as expected under Building optional coverages. Shared Example of proposed screen entry with Paul W to help accommodate multiple Loc/Building needs. | AA86: Building and under Personal Property | AB86: Commercial Property Coverage Part, Standard Property Policy | AE86: LI-CF-2008-059 | AF86: CF-2007-OFR07
A87: PR | B87: ISO | D87: CP10540607 | E87: =VLOOKUP(LOWER(TRIM(D87)),'Property Forms Usage'!#REF!,1,0) -> #REF! | F87: WINDSTORM OR HAIL EXCLUSION | I87: 39783 | K87: 74 | L87: 69 | N87: variable | Q87: Yes | R87: Yes | S87: Variable | T87: Automatic | U87: Y | V87: N | W87: N | X87: Buildings Tab/Location 1 Building 1 tab/under additional exclusions - check Exclude Windstorm and Hail/Building Coverage tab/under additional exclusions - check Exclude Windstorm and Hail/Business Personal Property tab/under additional exclusions - check Exclude Windstorm and Hail/Business Income tab/ under additional exclusions - check Exclude Windstorm and Hail | AB87: Causes of Loss-Basic Form, Causes of Loss-Broad Form, Causes of Loss-Special Form, Standard Property Policy | AE87: LI-CF-2008-059 | AF87: CF-2007-OFR07
A88: PR | B88: ISO | D88: CP10550607 | E88: =VLOOKUP(LOWER(TRIM(D88)),'Property Forms Usage'!#REF!,1,0) -> #REF! | F88: VANDALISM EXCLUSION | I88: 39783 | K88: 70 74 | N88: variable | Q88: Yes | R88: Yes | S88: Variable | T88: Automatic | U88: Y | V88: N | W88: N | X88: Buildings tab/Location 1 Building 1 tab/under additional exclusions - check Exclude Vandalism box/Building Coverage tab/under additional exclusions - check Exclude Vandalism box. | AB88: Causes of Loss-Basic Form, Causes of Loss-Broad Form, Causes of Loss-Special Form | AE88: LI-CF-2008-059 | AF88: CF-2007-OFR07
A89: PR | B89: ISO | D89: CP10560607 | E89: =VLOOKUP(LOWER(TRIM(D89)),'Property Forms Usage'!#REF!,1,0) -> #REF! | F89: SPRINKLER LEAKAGE EXCLUSION | I89: 39783 | K89: 70 74 | N89: variable | Q89: Yes | R89: Yes | S89: Variable | T89: Automatic | U89: Y | V89: N | W89: N | X89: Buildings tab/Location 1 Building 1 tab/under additional exclusions - check Exclude Sprinkler Leakage (Non-Sprinkler Rated Exposure)/Building Coverage tab/under additional exclusions - check Exclude Sprinkler Leakage (Non- Sprinkler Rated Exposure)/do the same for each addtional location or building | AB89: Causes of Loss-Basic Form, Causes of Loss-Broad Form, Causes of Loss-Special Form | AE89: LI-CF-2008-059 | AF89: CF-2007-OFR07
A90: PR | B90: ISO | D90: CP10600788 | E90: =VLOOKUP(LOWER(TRIM(D90)),'Property Forms Usage'!#REF!,1,0) -> #REF! | F90: MOLTEN MATERIAL | I90: 39783 | K90: 74 | N90: Static | S90: Static | T90: Automatic | V90: n/a | X90: Select on bldg/bpp/bi screen | AB90: Causes of Loss-Basic Form, Causes of Loss-Broad Form, Standard Property Policy | AE90: CF-88-68 | AG90: (2)
A91: PR | B91: ISO | D91: CP10650607 | E91: =VLOOKUP(LOWER(TRIM(D91)),'Property Forms Usage'!#REF!,1,0) -> #REF! | F91: FLOOD COVERAGE ENDORSEMENT | K91: 76 | N91: Static | S91: Static | T91: Automatic | V91: n/a | X91: select in prop screen-fill out drop down-loc screen/check bx on bldg, bpp, bi, EE, SC screen | AB91: Commercial Property Coverage Part, Standard Property Policy | AE91: LI-CF-2008-059 | AF91: CF-2007-OFR07
A92: PR | B92: ISO | D92: CP10700788 | E92: =VLOOKUP(LOWER(TRIM(D92)),'Property Forms Usage'!#REF!,1,0) -> #REF! | F92: PIER AND WHARF ADDITIONAL COVERED CAUSES OF LOSS | I92: 39813 | K92: 74 | N92: Static | S92: Static | T92: Automatic | V92: n/a | X92: Broad/Basic cause of loss in bldg/BI/EE, check bx, fill out drop down (form not attaching 10/2/12) | AB92: Causes of Loss-Basic Form, Causes of Loss-Broad Form, Standard Property Policy | AE92: CF-88-68
A93: PR | B93: ISO | D93: CP11050402 | E93: =VLOOKUP(LOWER(TRIM(D93)),'Property Forms Usage'!#REF!,1,0) -> #REF! | F93: BUILDERS RISK REPORTING FORM | I93: 39813 | K93: 41.A | L93: 41.B | N93: variable | Q93: Yes | R93: Yes | S93: Variable | T93: Automatic | U93: Y | V93: N | W93: N | X93: Buildings/ Loc Bldg/ Building Info section - choose Class Code 1150 for Builder's Risk/Building Coverage tab- select Reporting checkbox. | Z93: blocking this portion of rule | AA93: Building | AB93: Builders' Risk Coverage Form, Builders' Risk Changes-Standard Property Policy | AE93: LI-CF-2002-107 | AF93: CF-2001-O01FR
A94: PR | B94: ISO | D94: CP11060607 | E94: =VLOOKUP(LOWER(TRIM(D94)),'Property Forms Usage'!#REF!,1,0) -> #REF! | F94: BUILDERS' RISK PREMIUM ADJUSTMENT FORM | K94: 41 | N94: variable | Q94: Yes | R94: Yes | S94: Variable | T94: Automatic | U94: Per Mary Jo Lets skip this one for now | X94: comml pkg-bldg loc - property coverage - select business income - in bus inc screen, choose covg options "premium adjustment" | AB94: n/a | AE94: LI-CF-2008-059 | AF94: CF-2007-OFR07
A95: PR | B95: ISO | D95: CP11130695 | E95: =VLOOKUP(LOWER(TRIM(D95)),'Property Forms Usage'!#REF!,1,0) -> #REF! | F95: BUILDERS RISK RENOVATIONS | I95: 39813 | K95: 41 | N95: variable | Q95: Yes | R95: Yes | S95: Variable | T95: Automatic | U95: Y | V95: N | W95: N | X95: Building Tab/Location 1 Building 1 Tab- under building information- select Class Code 1150 for Builder's Risk/Building Coverage Tab/under Builder's Risk options check Renovations box | AA95: Building | AB95: Builders' Risk Coverage Form, Builders' Risk Changes-Standard Property Policy | AG95: (2)
A96: PR | B96: ISO | D96: CP11140788 | E96: =VLOOKUP(LOWER(TRIM(D96)),'Property Forms Usage'!#REF!,1,0) -> #REF! | F96: BUILDERS RISK - SEPARATE OR SUB-CONTRACTOR'S EXCLUSION | I96: 39813 | K96: 41 | N96: variable | Q96: Yes | R96: Yes | S96: Variable | T96: Automatic | U96: Y | V96: N | W96: N | X96: Building tab/Location 1 Building 1 tab/under building information- select Class Code 1150 for Builder's Risk/Building Coverage tab/under Builders Risk Options- check Separate or Sub-contractor exclusion box | AA96: Building | AB96: Builders' Risk Coverage Form, Builders' Risk Changes-Standard Property Policy | AE96: CF-88-68
A97: PR | B97: ISO | D97: CP11150788 | E97: =VLOOKUP(LOWER(TRIM(D97)),'Property Forms Usage'!#REF!,1,0) -> #REF! | F97: BUILDERS RISK - SEPARATE OR SUB-CONTRACTORS COVERAGE | I97: 39813 | K97: 41 | N97: variable | Q97: Yes | R97: Yes | S97: Variable | T97: Automatic | U97: Y | V97: N | W97: N | X97: Building tab/Location 1 Building 1 tab/under building information- select Class Code 1150 for Builder's Risk/Building Coverage tab/under Builders Risk Options- check Separate or Sub-contractor coverage option box | AA97: Building/not showing on Dec | AB97: Builders' Risk Coverage Form, Builders' Risk Changes-Standard Property Policy | AE97: CF-88-68 | AG97: (2)
A98: PR | B98: ISO | D98: CP11200607 | E98: =VLOOKUP(LOWER(TRIM(D98)),'Property Forms Usage'!#REF!,1,0) -> #REF! | F98: BUILDERS RISK - COLLAPSE DURING CONSTRUCTION | I98: 39813 | K98: 41 | N98: Static | S98: Static | T98: Automatic | V98: n/a | X98: 1150 Builder's risk code, on bldg screen select collapse option | AA98: Building | AB98: Builders' Risk Coverage Form | AE98: LI-CF-2008-059 | AF98: CF-2007-OFR07
A99: PR | B99: ISO | D99: CP11210695 | E99: =VLOOKUP(LOWER(TRIM(D99)),'Property Forms Usage'!#REF!,1,0) -> #REF! | F99: BUILDERS RISK - THEFT OF BUILDING MATERIALS, FIXTURES, MACHINERY, EQUIPMENT | G99: AZ | I99: 39813 | K99: 41 | N99: variable | Q99: Yes | R99: Yes | S99: Variable | T99: Automatic | U99: Y | V99: N | W99: N | X99: Building tab/Location 1 Building 1 tab/under building information-select Class code 1150 for Builder's risk/Building Coverage tab/under Builder's Risk options- select theft of bldg materials, then fill out new screen | AA99: Building/ yes, showing on Dec | AB99: Builders' Risk Coverage Form | AG99: (2)
A100: PR | B100: ISO | D100: CP11210695 | E100: =VLOOKUP(LOWER(TRIM(D100)),'Property Forms Usage'!#REF!,1,0) -> #REF! | F100: BUILDERS RISK - THEFT OF BUILDING MATERIALS, FIXTURES, MACHINERY, EQUIPMENT | G100: CO | I100: 39813 | K100: 41 | N100: variable | Q100: Yes | R100: Yes | S100: Variable | T100: Automatic | U100: Y | V100: N | W100: N | X100: Building tab/Location 1 Building 1 tab/under building information-select Class code 1150 for Builder's risk/Building Coverage tab/under Builder's Risk options- select theft of bldg materials, then fill out new screen | AA100: Building/ yes, showing on Dec | AB100: Builders' Risk Coverage Form | AG100: (2)
...

Sheet PCM Dropdowns (HIDE)
A1: PCM Dropdowns/Options
A4: COVERAGE LEVEL | B4: CLAIMS BASIS | C4: COVERAGE REQUIREMENT | D4: COVERAGE SCOPE | E4: COVERAGE EFFECT | F4: PREMIUM GENERATING? | G4: RATING BUREAU? | H4: PROPRIETARY
A5: Policy | B5: Occurrence | C5: Mandatory | D5: First Party | E5: Grants Coverage | F5: Yes | G5: N/A | H5: Yes
A6: Unit | B6: Claims-made | C6: Optional | D6: Third Party | E6: Restricts | F6: No | G6: ISO | H6: No
C7: Conditional | E7: Broadens | G7: AAIS
E8: Amends | G8: NCCI
E9: Adminstrative | G9: State
